<author lang="ar">
	<documents>
		<document><![CDATA[Ø§Ù„Ù†Ø§Ø¦Ø¨ Ø§Ù„Ø§Ø±Ø¯Ù†ÙŠ ÙˆÙ‡Ùˆ ØµØºÙŠØ± ... ðŸ˜‚
ÙƒÙ„Ùˆ Ø¨Ø±ÙØ¹ Ø§ÙŠØ¯Ùˆ #Ù…ÙˆØ§ÙÙ‚ Ùˆ #Ø«Ù‚Ù‡ https://t.co/P7IpXNwp4M]]></document>
		<document><![CDATA[Ø´Ø§Ø¯ÙŠ Ø¨Ù„Ø§Ù„ Ù…Ø­Ù…Ø¯ ÙØ±ÙŠØ­Ø§Øª Ù…Ø¶ÙŠØ¹ Ù‡ÙˆÙŠÙ‡ Ø§Ø­ÙˆØ§Ù„ Ù…Ø¯Ù†ÙŠÙ‡
Ø§Ù„ÙŠ Ø¨ÙŠØ¹Ø±ÙÙ‡ ÙŠØ±Ø§Ø¬Ø¹ Ø§Ù„ØµÙØ­Ù‡ Ø§Ùˆ Ø§Ù„Ø³ÙŠØ¯ Ø­Ø³ÙŠÙ† Ø¥Ø¨Ø±Ø§Ù‡ÙŠÙ… ÙØ±ÙŠØ­Ø§Øª
 Ø§Ù„Ù„ÙŠ Ø¨ÙŠØ¹Ø±ÙÙ‡... https://t.co/9YoNxRgARI]]></document>
		<document><![CDATA[#Ø§Ù„Ø¯Ø®Ø§Ù† ÙŠØ¤Ø¯ÙŠ Ù„Ù„Ù…ÙˆØª Ø§Ù„Ø¨Ø·ÙŠØ¦... ÙØ§Ù„Ø­ÙƒÙˆÙ…Ù‡ Ø±ÙØ¹Øª Ø³Ø¹Ø±Ùˆ Ø¹Ø´Ø§Ù† Ø§Ù„Ø´Ø¹Ø¨ ÙŠÙ…ÙˆØª Ø¨Ø³Ø±Ø¹Ù‡...
#Das_Auto Ù‡Ø§Ù„ÙˆØ²ÙŠØ±]]></document>
		<document><![CDATA[Ø¹Ù…Ø±Ùƒ Ø´ÙØª Ù…Ø¨Ø§Ø±Ø§Ù‡ Ø¨ØªØ¨Ù„Ø´ 1:0 ðŸ˜‚
#Ø§Ù„ÙˆØ­Ø¯Ø§Øª #Ø§Ù„ÙˆØ­Ø¯Ù‡]]></document>
		<document><![CDATA[Ø§Ù„Ø­ÙƒÙˆÙ…Ø© ØªØ·Ù„Ù‚ Ø­Ù…Ù„Ø© #Ø³ÙƒØ±_Ø«Ù…Ùƒ Ø±Ø¯Ø§ Ø¹Ù„Ù‰ Ø­Ù…Ù„Ø© #Ø³ÙƒØ±_Ø®Ø·Ùƒ...]]></document>
		<document><![CDATA[Ø®Ø·Ùƒ Ø§Ø´ØªØ±Ø§ÙƒÙ‡ #Ù…Ø¯ÙÙˆØ¹_Ù…Ø³Ø¨Ù‚Ø§ ÙˆÙ…Ù‚Ø§Ø·Ø¹ ..!!!
Ø²ÙŠ Ø§Ù„Ø¨Ù†Øª Ø§Ù„Ù„ÙŠ Ø¨ØªØ­Ø¨ Ù…Ù† ØªØ­Øª Ø§Ù„Ø­Ø±Ø§Ù… ÙˆØ§Ù‡Ù„Ù‡Ø§ Ù…ÙÙƒØ±ÙŠÙ†Ù‡Ø§ Ù†Ø§ÙŠÙ…Ù‡ ðŸ˜•]]></document>
		<document><![CDATA[ÙˆÙŠÙ† Ø¬Ù…Ø§Ø¹Ø© #pray_for_Ù…Ø§_ÙŠØ·Ù„Ø¨Ù‡_Ø§Ù„Ù…Ø³ØªÙ…Ø¹ÙˆÙ†
Ù…Ø§ Ø­Ø¯Ø§Ø´ Ø­Ø· pray for Canada ...ØŸ
ÙˆÙ„Ø§ Ø¹Ø´Ø§Ù† Ø§Ù„Ø¶Ø­Ø§ÙŠØ§ Ù…Ø³Ù„Ù…ÙŠÙ† ...!!!]]></document>
		<document><![CDATA[Ø§Ù„Ù…Ù„Ù‚ÙŠ ÙˆÙˆØ²ÙŠØ± Ø§Ù„Ø§Ø´ØºØ§Ù„ Ø­ÙƒÙˆ Ø§Ù†Ùˆ Ø·Ø±ÙŠÙ‚ #Ø§Ø±Ø¨Ø¯ #Ø¬Ø±Ø´ #Ø¹Ù…Ø§Ù† Ø§Ù„Ø¨Ø¯ÙŠÙ„Ù‡ Ø±Ø§Ø­ ØªØ¬Ù‡Ø² Ø®Ù„Ø§Ù„ ÙŠÙˆÙ…ÙŠÙ† ... ÙÙ…Ø´ Ø¶Ø±ÙˆØ±ÙŠ ÙƒÙ„ Ø´Ù‡Ø±ÙŠÙ† ØªÙØ¶Ø­ÙˆØ§... https://t.co/IjjDlS4v9o]]></document>
		<document><![CDATA[Ù†Ø¸Ø§Ù… #Ø§Ù„Ø­ÙƒÙˆÙ…Ù‡_Ø§Ù„Ø§Ø±Ø¯Ù†ÙŠÙ‡:
-Ø¨Ø­Ø°Ø±ÙˆÙƒ Ù…Ù† Ø§Ù„Ø¬ÙˆÙƒØ± ... Ø¨ØªØ³Ù„Ùƒ Ø¨Ø§Ù„Ø¯Ø®Ø§Ù† ...Ø¨Ø±ÙØ¹Ùˆ Ø§Ù„Ø¯Ø®Ø§Ù†.
-Ø¨ØªÙ‚Ø±Ø£ Ø§Ù†Ùˆ #Ø§Ù„Ø®Ø¶Ø±ÙˆØ§Øª Ø¨ØªØ³Ø§Ø¹Ø¯ Ø¨ØªØ±Ùƒ... https://t.co/PSGdTu29RZ]]></document>
		<document><![CDATA[Ø±Ø§Ø­ Ø¹Ù„ÙŠ Ø§Ø¯Ø§Ø¡ Ø§Ù„Ù‚Ø³Ù… ØªØ¨Ø¹ #ØªØ±Ø§Ù…Ø¨...
Ø´Ùˆ Ù‚Ø§Ù„ Ù…ÙˆÙƒÙ„Ø© ÙˆÙ„Ø§ Ù…ÙˆÙƒÙˆÙ„Ø© ØŸØŸØŸ]]></document>
		<document><![CDATA[Ù‚Ø§Ø¹Ø¯Ø© ØªÙˆØ²ÙŠØ¹ Ø§Ù„Ø«Ø±ÙˆØ§Øª ÙˆØ§Ù„Ù…Ù†Ø§ØµØ¨ ÙÙŠ #Ø§Ù„Ø£Ø±Ø¯Ù†...
Ø§Ù„Ø±Ø§ÙŠØ¨ Ù„Ù„Ù‚Ø±Ø§ÙŠØ¨ ... ÙˆØ§Ù„Ø²Ø¨Ø¯Ù‡ Ù„Ù„Ù†Ø³Ø§ÙŠØ¨ ... ÙˆØ§Ù„Ø´Ù†ÙŠÙ†Ù‡ Ù„Ù„Ø­Ø²ÙŠÙ†Ù‡.]]></document>
		<document><![CDATA[ÙˆÙ„Ø§ ÙƒØ£Ù†Ù‡ Ø«Ø§Ù†ÙŠ ÙŠÙˆÙ… #Ù†Ø§ØµØ±_Ø¬ÙˆØ¯Ù‡ Ù…Ø´ ÙˆØ²ÙŠØ± Ø®Ø§Ø±Ø¬ÙŠÙ‡ ðŸ˜’]]></document>
		<document><![CDATA[Ø´Ùˆ Ø¨ØªØ³ØªÙ†Ù‰ Ù…Ù† Ø´Ø¹Ø¨ Ø¨Ù‚Ø¯Ù… Ø§Ù„Ø®ÙŠØ§Ø± Ø¨ØµØ­Ù† Ø§Ù„ÙÙˆØ§ÙƒÙ‡ ...
Ø§Ø°Ø§ ÙˆØ²ÙŠØ± Ø§Ù„Ø´Ø¨Ø§Ø¨ Ù…ÙˆØ§Ù„ÙŠØ¯ 1937 ðŸ‘´]]></document>
		<document><![CDATA[Ø¨Ù‚ØªØ±Ø­ Ø¹ Ø±Ø¦ÙŠØ³ Ø§Ù„ÙˆØ²Ø±Ø§Ø¡ Ø¥Ø¹Ù„Ø§Ù† Ø§Ù„ØªØ´ÙƒÙŠÙ„Ø© Ø§Ù„Ø­ÙƒÙˆÙ…ÙŠØ© Ø¹ #Ø³Ù†Ø§Ø¨_Ø´Ø§Øª #Ø²ÙŠÙ†_ÙƒØ±Ø²ÙˆÙ† Ø¹Ø´Ø§Ù† Ù…ØªØ§Ø¨Ø¹ÙŠÙ†Ù‡Ø§ Ø§ÙƒØ«Ø± Ù…Ù† Ù…ØªØ§Ø¨Ø¹ÙŠÙ†... https://t.co/j2cIFCEWag]]></document>
		<document><![CDATA[Ø¨Ù‚ØªØ±Ø­ Ø¹ Ø±Ø¦ÙŠØ³ Ø§Ù„ÙˆØ²Ø±Ø§Ø¡ Ø¥Ø¹Ù„Ø§Ù† Ø§Ù„ØªØ´ÙƒÙŠÙ„Ø© Ø§Ù„Ø­ÙƒÙˆÙ…ÙŠØ© Ø§Ù„Ù‚Ø§Ø¯Ù…Ø© Ø¹Ø¨Ø± #Ø³Ù†Ø§Ø¨_Ø´Ø§Øª #Ø²ÙŠÙ†_ÙƒØ±Ø²ÙˆÙ† Ø¹Ø´Ø§Ù† Ù…ØªØ§Ø¨Ø¹ÙŠÙ†Ù‡Ø§ Ø§ÙƒØ«Ø± Ù…Ù† Ù…ØªØ§Ø¨Ø¹ÙŠÙ†... https://t.co/e96fQozIPv]]></document>
		<document><![CDATA[Ø¨ÙŠØ§Ù† Ø§Ù„Ù…ØªÙ‚Ø§Ø¹Ø¯ÙŠÙ† Ø§Ù„Ø¹Ø³ÙƒØ±ÙŠÙŠÙ† Ø¨ÙŠØ§Ù† Ù…Ø³Ù‚Ø¹ ÙˆØ¬Ù‡ ...
ÙŠØ­Ù…Ù„ÙˆÙ† Ø§Ù„Ù…Ù„Ùƒ Ù…Ø³Ø¦ÙˆÙ„ÙŠØ© Ø³Ù„Ø§Ù…Ø© #Ø²Ù…ÙŠÙ„Ù‡Ù… Ø§Ù„Ù…Ø¹ØªÙ‚Ù„...!!! ÙˆÙƒØ£Ù†Ù‡ Ø¹Ù†Ø§ Ø³ÙˆØ§Ø¨Ù‚ Ø¨Ù‚ØªÙ„... https://t.co/8CZ9MpzNAt]]></document>
		<document><![CDATA[#ÙˆÙŠÙ†Ùƒ_ÙŠØ§_Ø®Ø´Ø¨_Ù„Ù…Ø§_ÙƒÙ†Ø§_Ù†Ø¬Ø§Ø±ÙŠÙ†
-Ø´Ùˆ Ø¨Ø¯Ùƒ ØªØ´ØªØºÙ„ Ø¨Ø¹Ø¯ Ù…Ø§ ØªØªÙ‚Ø§Ø¹Ø¯
-Ø¨Ø¯ÙŠ Ø§ØµÙŠØ± Ù…Ø¹Ø§Ø±Ø¶
ÙˆØ¨Ø±ÙˆØ­ Ø¨ÙƒØªØ¨ Ø³Ø·Ø±ÙŠÙ† ÙˆÙ…Ø§ Ø­Ø¯Ø§Ø´ Ø¹Ø§Ø±Ù Ø¹Ù†Ù‡...ÙˆØ¨Ø³... https://t.co/aEKK5znvby]]></document>
		<document><![CDATA[-Ø´Ùˆ Ø¨Ø¯Ùƒ ØªØ´ØªØºÙ„ Ø¨Ø¹Ø¯ Ù…Ø§ ØªØªÙ‚Ø§Ø¹Ø¯
-Ø¨Ø¯ÙŠ Ø§ØµÙŠØ± Ù…Ø¹Ø§Ø±Ø¶
ÙˆØ¨Ø±ÙˆØ­ Ø¨ÙƒØªØ¨ Ø³Ø·Ø±ÙŠÙ† ÙˆÙ…Ø§ Ø­Ø¯Ø§Ø´ Ø¹Ø§Ø±Ù Ø¹Ù†Ù‡...ÙˆØ¨Ø³ ÙŠØ¹ØªÙ‚Ù„ÙˆÙ‡ Ø¨Ù‚ÙˆÙ„Ùˆ Ø§Ø¹ØªÙ‚Ù„ÙˆÙ‡ Ø¹Ø´Ø§Ù†... https://t.co/rEpuaomfwJ]]></document>
		<document><![CDATA[Ù…Ø³Ù„Ø³Ù„ #the_simpsons ÙŠØªÙ†Ø¨Ø£ Ø¨Ø­ÙƒÙˆÙ…Ø© #Ø§Ù„Ø´Ù„ÙŠØ­ Ù…Ù†Ø° Ø¹Ø§Ù… 2000 !
ÙƒÙ„ Ù…Ø§ ØªÙ†Ø²Ù†Ù‚ Ø§Ù„Ø­ÙƒÙˆÙ…Ù‡ Ø¥Ø¦Ù„Ø¹... Ø§Ù„Ø´Ø±Ù Ø¨Ø±ÙˆØ­ ÙˆØ¨ÙŠØ¬ÙŠ Ø¹Ø§Ø¯ÙŠ... Ø¨Ø³... https://t.co/6mgUJBTTGD]]></document>
		<document><![CDATA[Ø³ØªØªÙˆÙ‚Ù #Ø§Ù„Ù†Ø§Ø³_Ø§Ù„Ø·ÙØ±Ø§Ù†Ù‡ Ø¹Ù† Ø§ÙƒÙ„ Ø§Ù„Ø²Ø¨Ø§Ù„Ù‡ Ù„Ù…Ø§ ØªØªÙˆÙ‚Ù #Ø§Ù„Ù†Ø§Ø³_Ø§Ù„Ø²Ø¨Ø§Ù„Ù‡ Ø¹Ù† Ø§ÙƒÙ„ Ø­Ù‚ÙˆÙ‚ Ø§Ù„Ù†Ø§Ø³ Ø§Ù„Ø·ÙØ±Ø§Ù†Ù‡...]]></document>
		<document><![CDATA[Ø³ØªØªÙˆÙ‚Ù #Ø§Ù„Ù†Ø§Ø³_Ø§Ù„Ø·ÙØ±Ø§Ù†Ù‡ Ø¹Ù† Ø§Ù„Ø§ÙƒÙ„ Ù…Ù† Ø§Ù„Ø²Ø¨Ø§Ù„Ù‡ Ù„Ù…Ø§ ØªØªÙˆÙ‚Ù #Ø§Ù„Ù†Ø§Ø³_Ø§Ù„Ø²Ø¨Ø§Ù„Ù‡ Ø¹Ù† Ø§ÙƒÙ„ Ø­Ù‚ÙˆÙ‚ Ø§Ù„Ù†Ø§Ø³ Ø§Ù„Ø·ÙØ±Ø§Ù†Ù‡...]]></document>
		<document><![CDATA[ÙƒÙ„ Ø¹Ù„Ù… ÙˆØ§Ù†ØªÙŠ Ø¨Ø®ÙŠØ± ÙˆØ³Ù†Ø© Ø®ÙŠØ± Ø¹Ù„ÙŠÙƒÙŠ Ø§Ù† Ø´Ø§Ø¡ Ø§Ù„Ù„Ù‡... Ø§Ù„Ù„Ù‡ ÙŠØ®Ù„ÙŠÙ„Ù†Ø§ Ø§ÙŠØ§ÙƒÙŠ ÙˆÙŠØ¯ÙŠÙ… Ø¹Ù„ÙŠÙƒÙŠ Ø§Ù„ØµØ­Ù‡ ÙˆØ§Ù„Ø¹Ø§ÙÙŠÙ‡ ÙŠØ§ Ø±Ø¨ .]]></document>
		<document><![CDATA[Ø¨Ø­Ø¨ Ø§Ø­ÙƒÙŠ Ù„Ù„Ù…ØºØªØ±Ø¨ÙŠÙ† Ø§Ù„Ø§Ø±Ø¯Ù†ÙŠÙŠÙ† ... Ø±Ø§Ø­Øª Ø¹Ù„ÙŠÙƒÙˆ ØªÙ†Ø²ÙŠÙ„Ø§Øª #Ø¶Ø±Ø§ØºÙ…Ù‡...!!!
Ø¨ÙƒØ±Ø§ Ø¨ØªÙ„Ø§Ù‚ÙŠ Ù†Øµ Ø§Ù„Ø§Ø±Ø¯Ù† Ù„Ø§Ø¨Ø³ÙŠÙ† Ù†ÙØ³ Ø§Ù„Ø¨ÙŠØ¬Ø§Ù…Ù‡... #Ø´Ø¹Ø¨_ÙˆØ§Ø­Ø¯]]></document>
		<document><![CDATA[#Ø§Ù„Ø°ÙƒØ±Ù‰_Ø§Ù„Ø¹Ø§Ø´Ø±Ù‡_Ù„Ø§Ø³ØªØ´Ù‡Ø§Ø¯_Ø§Ù„Ù…Ù‡ÙŠØ¨_ØµØ¯Ø§Ù…_Ø­Ø³ÙŠÙ†
Ø§Ù„Ø­Ù‚ Ù…Ø§ Ø´Ù‡Ø¯ Ø¨Ù‡ Ø§Ù„Ø§Ø¹Ø¯Ø§Ø¡ ...
Ø§Ø°Ø§ Ø§Ù„Ø´ÙŠØ¹Ù‡ Ø§Ù„Ø§Ù† ÙˆÙ‡Ù… Ù…Ù† ÙŠÙ…Ù„ÙƒÙˆÙ† ÙƒÙ„ Ø§Ù„Ø§Ù…ØªÙŠØ§Ø²Ø§Øª... https://t.co/ijxF5b10Aj]]></document>
		<document><![CDATA[ØµÙ„Ø§Ø© Ø¬Ù…Ø¹Ù‡ ÙˆÙ„Ø§ Ù…Ø¤ØªÙ…Ø± ØµØ­ÙÙŠ Ù‡Ø§ÙŠ ØŸØŸ!!
#Ø§Ù„ØªÙ…Ø§Ø³_Ø§Ø«Ø± ÙÙŠ #Ø§Ù„ÙƒØ±Ùƒ
#Ø´Ø¬Ø±Ù‡]]></document>
		<document><![CDATA[Ù„Ù„Ø­ÙØ§Ø¸ Ø¹Ù„Ù‰ Ø³Ø±ÙŠØ© Ø§Ù„ØªØ­Ù‚ÙŠÙ‚ ÙˆØ³Ù„Ø§Ù…Ø© Ø§Ù„Ø¹Ù…Ù„ÙŠÙ‡ Ø§Ù„Ø§Ù…Ù†ÙŠÙ‡...Ø§Ù„Ø±Ø¬Ø§Ø¡ Ø¹Ø¯Ù… Ù†Ù‚Ù„ Ø§ÙŠ Ù…Ø¹Ù„ÙˆÙ…Ù‡ Ù…Ù† Ù…ØµØ§Ø¯Ø± ØºÙŠØ± Ù…ÙˆØ«ÙˆÙ‚Ù‡ ÙƒÙ€ #ÙˆØ²ÙŠØ±_Ø§Ù„Ø§Ø¹Ù„Ø§Ù… Ù…Ø«Ù„Ø§...ðŸ‘Œ]]></document>
		<document><![CDATA[Ù„Ù„Ø­ÙØ§Ø¸ Ø¹Ù„Ù‰ Ø³Ø±ÙŠØ© Ø§Ù„ØªØ­Ù‚ÙŠÙ‚ ÙˆØ³Ù„Ø§Ù…Ø© Ø§Ù„Ø¹Ù…Ù„ÙŠÙ‡ Ø§Ù„Ø§Ù…Ù†ÙŠÙ‡...Ø§Ù„Ø±Ø¬Ø§Ø¡ Ø¹Ø¯Ù… Ù†Ù‚Ù„ Ø§ÙŠ Ù…Ø¹Ù„ÙˆÙ…Ù‡ Ù…Ù† Ù…ØµØ§Ø¯Ø± ØºÙŠØ± Ù…ÙˆØ«ÙˆÙ‚Ù‡ Ø²ÙŠ #ÙˆØ²ÙŠØ±_Ø§Ù„Ø§Ø¹Ù„Ø§Ù… Ù…Ø«Ù„Ø§...ðŸ‘Œ]]></document>
		<document><![CDATA[Ù„Ù„Ø­ÙØ§Ø¸ Ø¹Ù„Ù‰ Ø³Ø±ÙŠØ© Ø§Ù„ØªØ­Ù‚ÙŠÙ‚Ø§Øª ÙˆØ³Ù„Ø§Ù…Ø© Ø§Ù„Ø¹Ù…Ù„ÙŠÙ‡ Ø§Ù„Ø§Ù…Ù†ÙŠÙ‡ ... Ø§Ù„Ø±Ø¬Ø§Ø¡ Ø¹Ø¯Ù… Ù†Ù‚Ù„ Ø§ÙŠ Ù…Ø¹Ù„ÙˆÙ…Ù‡ Ù…Ù† Ù…ØµØ§Ø¯Ø± ØºÙŠØ± Ù…ÙˆØ«ÙˆÙ‚Ù‡
ÙƒÙ€ #ÙˆØ²ÙŠØ±_Ø§Ù„Ø§Ø¹Ù„Ø§Ù… Ù…Ø«Ù„Ø§...ðŸ‘Œ]]></document>
		<document><![CDATA[ØªØµØ±ÙŠØ­Ø§Øª ÙˆØ²ÙŠØ± Ø§Ù„Ø§Ø¹Ù„Ø§Ù… Ø¨Ø§Ù„Ù…Ø¤ØªÙ…Ø± Ø§Ù„ØµØ­ÙÙŠ Ø²ÙŠ Ø§Ù„Ø¹Ø±ÙˆØ³ Ø§Ù„Ø¬Ø¯ÙŠØ¯Ù‡...
Ø¨ØªÙÙˆØª Ø¹ Ø§Ù„Ù…Ø·Ø¨Ø® Ø³Ø¨Ø¹ Ø³Ø§Ø¹Ø§Øª Ùˆ Ø¨ØªØ·Ù„Ø¹ Ø¨Ù‚Ù„Ø§ÙŠØ© Ø¨ÙŠØ¶...
#Ø§Ù„ÙƒØ±Ùƒ]]></document>
		<document><![CDATA[Ø§Ù„Ù„Ù‡Ù… Ø¥Ù†ÙÙ‘Ø§ Ø§Ø³ØªÙˆØ¯Ø¹Ù†Ø§Ùƒ #Ø±Ø¬Ø§Ù„_Ø§Ù„Ø£Ù…Ù† ÙˆØ£Ù…Ù† #Ø§Ù„Ø§Ø±Ø¯Ù† ...]]></document>
		<document><![CDATA[Ù‚Ø§Ù„ Ù…Ø¨Ø³ÙˆØ·ÙŠÙ† Ø§Ù†Ùˆ Ø§ØºØªØ§Ù„ Ø§Ù„Ø³ÙÙŠØ± #Ø§Ù„Ø±ÙˆØ³ÙŠ Ø¹Ø´Ø§Ù† Ø­Ù„Ø¨ ÙˆØ§Ù†Ùˆ Ø§Ù„Ø§ØªØ±Ø§Ùƒ Ø¹Ù†Ø¯Ù‡Ù… Ø¹Ø±ÙˆØ¨Ù‡ Ø§ÙƒØ«Ø± Ù…Ù† #Ø§Ù„Ø¹Ø±Ø¨
Ø·ÙŠØ¨ Ù„ÙŠØ´ Ù…Ø§ Ø§ØºØªØ§Ù„ÙˆØ§ Ø§Ù„Ø³ÙÙŠØ±... https://t.co/pOI6TR2XnH]]></document>
		<document><![CDATA[Ù‚Ø§Ù„ Ù…Ø¨Ø³ÙˆØ·ÙŠÙ† Ø§Ù†Ùˆ Ø§ØºØªØ§Ù„ Ø§Ù„Ø³ÙÙŠØ± #Ø§Ù„Ø±ÙˆØ³ÙŠ Ø¹Ø´Ø§Ù† Ø­Ù„Ø¨ ÙˆØ§Ù†Ùˆ Ø§Ù„Ø§ØªØ±Ø§Ùƒ Ø¹Ù†Ø¯Ù‡Ù… Ø¹Ø±ÙˆØ¨Ù‡ Ø§ÙƒØ«Ø± Ù…Ù† #Ø§Ù„Ø¹Ø±Ø¨
Ø·ÙŠØ¨ Ù„ÙŠØ´ Ù…Ø§ Ø§ØºØªØ§Ù„ÙˆØ§ Ø§Ù„Ø³ÙÙŠØ±... https://t.co/NkYaa8tbMI]]></document>
		<document><![CDATA[Ø§Ù„ØªÙ„ÙØ²ÙŠÙˆÙ† #Ø§Ù„Ø±ÙˆØ³ÙŠ ÙŠØ¨Ø« Ø§Ù„Ø¢Ù† Ø¨Ø±Ù†Ø§Ù…Ø¬ Ø¹Ù† ÙÙˆØ§Ø¦Ø¯ Ø§Ù„ÙÙˆØ¯ÙƒØ§!! Ø¨Ø¥Ù†ØªØ¸Ø§Ø± Ø§Ù„Ù…Ø¤ØªÙ…Ø± Ø§Ù„ØµØ­ÙÙŠ...
#Ù…Ù†Ù‚ÙˆÙ„]]></document>
		<document><![CDATA[Ù…ÙŠÙ† Ø§Ù„Ù…Ø³Ø¦ÙˆÙ„ Ø¹Ù† ÙƒØ°Ø¨Ø© ÙˆØ¬ÙˆØ¯ Ø±Ù‡Ø§Ø¦Ù† ÙÙŠ Ù‚Ù„Ø¹Ø© #Ø§Ù„ÙƒØ±Ùƒ ...ÙˆØ·Ù„Ø¹ Ù„Ø§ ÙÙŠ Ø±Ù‡Ø§Ø¦Ù† ÙˆÙ„Ø§ ÙÙŠ ÙƒÙ†Ø¯Ø±Ù‡ØŸ ÙŠØ¹Ù†ÙŠ ÙƒØ§Ù† Ø¨Ø§Ù…ÙƒØ§Ù†Ù‡Ù… ÙŠØªØ¹Ø§Ù…Ù„Ùˆ Ù…Ø¹... https://t.co/KJKIy4iKpk]]></document>
		<document><![CDATA[Ø§Ù†ØªÙ‡Ø§Ø¡ Ø§Ù„Ø¹Ù…Ù„ÙŠØ© Ø§Ù„Ø§Ù…Ù†ÙŠØ© ÙÙŠ Ù‚Ù„Ø¹Ø© #Ø§Ù„ÙƒØ±Ùƒ Ø¨Ø´ÙƒÙ„ ÙƒØ§Ù…Ù„ ÙˆØ§Ù„Ø­ØµÙŠÙ„Ù‡ 9 Ø´Ù‡Ø¯Ø§Ø¡ ÙˆÙˆÙØ§Ù‡ ÙƒÙ†Ø¯ÙŠÙ‡ ... Ùˆ 34 Ù…ØµØ§Ø¨ ... 4 Ù…Ù† Ø§Ù„Ø¯Ø±Ùƒ Ùˆ 11... https://t.co/ETDIq30Dwk]]></document>
		<document><![CDATA[Ù…Ø´ Ø®Ø§ÙŠÙÙŠÙ† Ù…Ù† #Ø§Ù„Ø®ÙˆØ§Ø±Ø¬ ... Ø§Ù„Ø®ÙˆÙ ØµØ§Ø± Ù…Ù† #Ø§Ù„Ø¯ÙˆØ§Ø®Ù„...!!! Ø§Ù„Ø¶ÙŠÙˆÙ Ø§Ù„ÙˆØ³Ø®Ù‡ Ø§Ù„Ù„ÙŠ Ø¬Ø§Ø¨Ù‡Ø§ ÙƒØ«Ø± Ø§Ù„ØªÙ‡Ù„ÙŠ...]]></document>
		<document><![CDATA[Ø¬Ø§ÙŠÙŠÙ† ÙŠØ­Ø§Ø±Ø¨ÙˆØ§ Ø´Ø¹Ø¨ Ø¨Ø­Ø· ÙˆØ§Ø³Ø·Ø© Ø¹Ø´Ø§Ù† ÙŠØªØ¬Ù†Ø¯ ÙˆÙŠØ±ÙˆØ­ Ø¹ Ø§Ù„Ø¬ÙŠØ´...
#Ø§Ù„ÙƒØ±Ùƒ #ÙØ²Ø¹Ø©_Ø§Ù„Ù†Ø´Ø§Ù…Ù‰]]></document>
		<document><![CDATA[Ø§Ù„Ø§Ø¬Ù‡Ø²Ù‡ Ø§Ù„Ø§Ù…Ù†ÙŠÙ‡ ØªØªØ¹Ø§Ù…Ù„ Ù…Ø¹ Ù…Ø³Ù„Ø­ÙŠÙ† Ù…ØªØ­ØµÙ†ÙŠÙŠÙ† ÙÙŠ Ù‚Ù„Ø¹Ø© Ø§Ù„ÙƒØ±Ùƒ ...!!!]]></document>
		<document><![CDATA[Ø§Ù„Ù„Ù‡ ÙŠØ±Ø­Ù… Ø£ÙŠØ§Ù… Ù…Ø§ ÙƒØ§Ù†Øª Ø£ÙƒØ¨Ø± Ù…Ø´Ø§ÙƒÙ„Ù†Ø§ Ø¨Ù€ #Ø§Ù„Ø£Ø±Ø¯Ù† Ø§Ù„Ø±Ø¹ÙŠ Ø§Ù„Ø¬Ø§Ø¦Ø± ÙˆØ§Ù„Ù‡Ø¬Ø±Ù‡ Ù…Ù† Ø§Ù„Ø±ÙŠÙ Ø§Ù„Ù‰ Ø§Ù„Ù…Ø¯ÙŠÙ†Ù‡...]]></document>
		<document><![CDATA[#Ø­Ù„Ø¨ ... 
Ù„Ø§Ø¶Ù„ Ø¹Ù†Ø§ Ù„Ø§ Ø­Ù…ÙŠØ© Ø§Ù„Ø¬Ø§Ù‡Ù„ÙŠØ© ÙˆÙ„Ø§ Ù†Ø®ÙˆØ© Ø§Ù„Ø§Ø³Ù„Ø§Ù…...]]></document>
		<document><![CDATA[#Ø§Ù„Ù…ÙˆÙ„Ø¯Ø§Ù„Ù†Ø¨ÙˆÙŠ 
Ø¹ÙŠØ´ Ø­ÙŠØ§ØªÙƒ Ø¨Ø£Ø®Ù„Ø§Ù‚ Ù†Ø¨ÙŠÙƒ ï·º ...]]></document>
		<document><![CDATA[#××‘××‘ ï·º
#Ø§Ù„Ù…ÙˆÙ„Ø¯_Ø§Ù„Ù†Ø¨ÙˆÙŠ]]></document>
		<document><![CDATA[Ø­Ø±Ø±ÙˆØ§ #Ø­Ù„Ø¨ Ù‚Ø§Ù„...!!! Ø­Ø±Ø±ÙˆÙ‡Ø§ Ù…Ù† Ø§Ù‡Ù„Ù‡Ø§
Ø­Ø±Ø±ÙˆÙ‡Ø§ #Ø±ÙˆØ³ÙŠØ§ Ùˆ #Ø§ÙŠØ±Ø§Ù† Ùˆ #Ø­Ø²Ø¨_Ø§Ù„Ù„Ø§Øª Ù…Ù† #Ø§Ù„ÙØ±Ù†Ø³Ø§ÙˆÙŠ Ù…Ø«Ù„Ø§ ... ÙˆÙ„Ø§ Ø­Ø±Ø±Ùˆ Ø§Ù„Ø¬ÙˆÙ„Ø§Ù†... https://t.co/tXG0VBdULi]]></document>
		<document><![CDATA[Ø±ÙˆØ§ÙŠØ© #Ø­Ø¯ÙŠØ«_Ø§Ù„Ø¬Ù†ÙˆØ¯ Ù„Ù„Ø±ÙˆØ§Ø¦ÙŠ #Ø§ÙŠÙ…Ù†_Ø§Ù„Ø¹ØªÙˆÙ… Ø¹Ø¯Ø¯ ØµÙØ­Ø§ØªÙ‡Ø§ 470 ØµÙØ­Ù‡ ÙˆØµØ§Ø­Ø¨Ø§ Ù‡Ø³Ø§ Ø¨Ø§Ù„Ø³Ø¬Ù† ...
ÙˆØªÙ‚Ø±ÙŠØ± #Ø¯ÙŠÙˆØ§Ù†_Ø§Ù„Ù…Ø­Ø§Ø³Ø¨Ù‡ Ø¹Ù†... https://t.co/ZwdCtRibqk]]></document>
		<document><![CDATA[Ø£Ù† ØªÙƒÙˆÙ† ÙƒØ§ØªØ¨Ù‹Ø§ Ù…Ø¹Ù†Ø§Ù‡ Ø£Ù† ØªÙØ¹Ø§Ù…Ù„ ÙƒÙ…Ø¬Ø±Ù…
ÙˆØ§Ù† ØªÙƒÙˆÙ† Ù…Ø¬Ø±Ù… Ù…Ø¹Ù†Ø§Ù‡ Ø§Ù† ØªØ¹Ø§Ù…Ù„ ÙƒÙˆØ²ÙŠØ±
#Ø§ÙŠÙ…Ù†_Ø¹ØªÙˆÙ… Ù…Ø³Ø¬ÙˆÙ† Ùˆ #ÙˆØ²ÙŠØ±_Ø§Ù„Ø¹Ù…Ù„ Ø­Ø± Ø·Ù„ÙŠÙ‚...!!!
#Ø­Ø¯ÙŠØ«_Ø§Ù„Ø¬Ù†ÙˆØ¯]]></document>
		<document><![CDATA[Ø§Ù„Ø¬Ù…Ù„ Ø¨Ù€ 4 Ø¯Ø±Ø§Ù‡Ù… ÙˆØ§Ù„Ù‚Ø· Ø¨Ù€ 400 Ø¯Ø±Ù‡Ù… ...
Ø­Ù‚ Ø·Ù‚Ù… ÙƒØ§Ø³Ø§Øª #ÙˆØ²ÙŠØ±_Ø§Ù„Ø¹Ù…Ù„ Ø¨Ù€ 180 Ø¯ÙŠÙ†Ø§Ø± Ø®Ù„Ø§ Ø§Ù„Ø´Ø¹Ø¨ ÙŠÙ†Ø³Ù‰ ÙØ³Ø§Ø¯ ÙˆØ³Ø±Ù‚Ø§Øª Ø¨Ø§Ù„Ù…Ù„Ø§ÙŠÙŠÙ† ...!!!]]></document>
		<document><![CDATA[Ø§Ù„Ø¬Ù…Ù„ Ø¨Ù€ 4 Ø¯Ø±Ø§Ù‡Ù… ÙˆØ§Ù„Ù‚Ø· Ø¨Ù€ 400 Ø¯Ø±Ù‡Ù… ...
Ø­Ù‚ Ø·Ù‚Ù… ÙƒØ§Ø³Ø§Øª #ÙˆØ²ÙŠØ±_Ø§Ù„Ø¹Ù…Ù„ Ø¨Ù€ 180 Ø¯ÙŠÙ†Ø§Ø± Ø®Ù„Ø§ Ø§Ù„Ø´Ø¹Ø¨ ÙŠÙ†Ø³Ø§ ÙØ³Ø§Ø¯ ÙˆØ³Ø±Ù‚Ø§Øª Ø¨Ø§Ù„Ù…Ù„Ø§ÙŠÙŠÙ† ...!!!]]></document>
		<document><![CDATA[ØªØ®ÙŠÙ„ Ø­Ø§Ù„Ùƒ Ø±Ø¦ÙŠØ³ ÙˆØ²Ø±Ø§Ø¡ #Ø§Ù„Ø§Ø±Ø¯Ù† Ø§Ù„Ø­Ø§Ù„ÙŠ ÙˆÙƒÙ„ Ø§Ù„Ø§Ø±Ø¯Ù†ÙŠÙŠÙ† Ø¨ØªØ±Ø­Ù…ÙˆØ§ Ø¹Ù„Ù‰ Ø±Ø¦ÙŠØ³ ÙˆØ²Ø±Ø§Ø¡ Ù‚Ø¨Ù„ 45 Ø³Ù†Ø© ... Ø¨ØªØ­Ø³ Ø­Ø§Ù„Ùƒ Ù…Ù„ÙƒÙŠØ´ Ø¯Ø§Ø¹ÙŠ Ø²ÙŠ... https://t.co/LDLOKazMKe]]></document>
		<document><![CDATA[ØªØ®ÙŠÙ„ Ø­Ø§Ù„Ùƒ Ø±Ø¦ÙŠØ³ ÙˆØ²Ø±Ø§Ø¡ #Ø§Ù„Ø§Ø±Ø¯Ù† Ø§Ù„Ø­Ø§Ù„ÙŠ ÙˆÙƒÙ„ Ø§Ù„Ø§Ø±Ø¯Ù†ÙŠÙŠÙ† Ø¨ØªØ±Ø­Ù…ÙˆØ§ Ø¹Ù„Ù‰ Ø±Ø¦ÙŠØ³ ÙˆØ²Ø±Ø§Ø¡ Ù‚Ø¨Ù„ 45 Ø³Ù†Ø© ... Ø¨ØªØ­Ø³ Ø­Ø§Ù„Ùƒ Ù…Ù„ÙƒÙŠØ´ Ø¯Ø§Ø¹ÙŠ Ø²ÙŠ... https://t.co/0OAGupZwuZ]]></document>
		<document><![CDATA[ØªØ®ÙŠÙ„ Ø­Ø§Ù„Ùƒ Ø±Ø¦ÙŠØ³ ÙˆØ²Ø±Ø§Ø¡ #Ø§Ù„Ø§Ø±Ø¯Ù† Ø§Ù„Ø­Ø§Ù„ÙŠ ÙˆÙƒÙ„ Ø§Ù„Ø§Ø±Ø¯Ù†ÙŠÙŠÙ† Ø¨ØªØ±Ø­Ù…ÙˆØ§ Ø¹Ù„Ù‰ Ø±Ø¦ÙŠØ³ ÙˆØ²Ø±Ø§Ø¡ Ù‚Ø¨Ù„ 45 Ø³Ù†Ø© ... Ø¨ØªØ­Ø³ Ø­Ø§Ù„Ùƒ Ù…Ù„ÙƒÙŠØ´ Ø¯Ø§Ø¹ÙŠ Ø²ÙŠ... https://t.co/HP3apoNmy5]]></document>
		<document><![CDATA[ØªØ®ÙŠÙ„ Ø­Ø§Ù†Ùƒ Ø±Ø¦ÙŠØ³ ÙˆØ²Ø±Ø§Ø¡ Ø§Ù„Ø£Ø±Ø¯Ù† Ø§Ù„Ø­Ø§Ù„ÙŠ ÙˆÙƒÙ„ Ø§Ù„Ø§Ø±Ø¯Ù†ÙŠÙŠÙ† Ø¨ØªØ±Ø­Ù…ÙˆØ§ Ø¹Ù„Ù‰ Ø±Ø¦ÙŠØ³ ÙˆØ²Ø±Ø§Ø¡ Ù‚Ø¨Ù„ 45 Ø³Ù†Ø© ... Ø¨ØªØ­Ø³ Ø­Ø§Ù„Ùƒ #Ù…Ø²Ù‡Ø±ÙŠØ© Ø²ÙŠ Ø§Ù„Ø­Ø§Ø±Ø³ Ù…Ø­Ù…Ø¯ Ø´Ø·Ù†Ø§ÙˆÙŠ...]]></document>
		<document><![CDATA[#Ù…ÙØ§Ø±Ù‚Ø§Øª...
#ÙˆØµÙÙŠ_Ø§Ù„ØªÙ„ #Ø§Ø±Ø¯Ù†ÙŠ ÙˆÙ„Ø¯ Ø¨Ø§Ù„Ø¹Ø±Ø§Ù‚ ÙˆØ¹Ø§Ø´ Ù„ÙÙ„Ø³Ø·ÙŠÙ† ÙˆØ§Ø³ØªØ´Ù‡Ø¯ ÙÙŠ Ø§Ù„Ù‚Ø§Ù‡Ø±Ù‡... ÙÙŠ Ø²Ù…Ù† #Ø¬Ù…Ø§Ù„_Ø¹Ø¨Ø¯Ø§Ù„Ù†Ø§ØµØ± Ø§Ø¨Ùˆ Ø§Ù„Ù‚ÙˆÙ…Ø¬ÙŠÙ‡... https://t.co/yl9jsAHLdu]]></document>
		<document><![CDATA[Ù…Ø§Ø¯Ø§Ù… Ø§Ù„Ø³Ø±Ø§Ø¬ ÙÙŠÙ‡ Ø²ÙŠØª  Ø®Ù„ÙˆÙ‡ Ø¶Ø§ÙˆÙŠ...
Ø°ÙƒØ±Ù‰ Ø§Ø³ØªØ´Ù‡Ø§Ø¯ Ø§Ù„Ø´Ù‡ÙŠØ¯ Ø§Ù„Ø¨Ø·Ù„ #ÙˆØµÙÙŠ_Ø§Ù„ØªÙ„ Ø±Ø­Ù…Ù‡ Ø§Ù„Ù„Ù‡ ...]]></document>
		<document><![CDATA[Ù…Ø§Ø¯Ø§Ù… Ø§Ù„Ø³Ø±Ø§Ø¬ ÙÙŠÙ‡ Ø²ÙŠØª  Ø®Ù„ÙˆÙ‡ Ø¶Ø§ÙˆÙŠ 
Ø°ÙƒØ±Ù‰ Ø§Ø³ØªØ´Ù‡Ø§Ø¯ Ø§Ù„Ø´Ù‡ÙŠØ¯ Ø§Ù„Ø¨Ø·Ù„ #ÙˆØµÙÙŠ_Ø§Ù„ØªÙ„ Ø±Ø­Ù…Ù‡ Ø§Ù„Ù„Ù‡ ...]]></document>
		<document><![CDATA[ÙÙŠ Ø¸Ù„ Ø§Ù„Ø¸Ø±ÙˆÙ Ø§Ù„ØµØ¹Ø¨Ù‡ Ø§Ù„ØªÙŠ ÙŠÙ…Ø± Ø¨Ù‡Ø§ Ø§Ù„Ø¨Ù„Ø§Ø¯ ÙˆØ§Ù„Ø¹Ø¨Ø§Ø¯ ... ØªØ£ØªÙŠ Ø§Ù„Ø±Ø³Ø§Ø¦Ù„ Ø§Ù„Ø³Ø±ÙŠÙ‡ ÙÙŠ #Ø¬Ù„Ø³Ø§Øª_ÙˆÙ†Ø§Ø³Ù‡ #Ù…Ø¬Ù„Ø³_Ø§Ù„Ù†ÙˆØ§Ø¨ ÙˆØ§Ù„ØªÙŠ ØªØ¶Ø§Ù‡ÙŠ... https://t.co/DItU1ufH44]]></document>
		<document><![CDATA[Ø°ÙƒØ±ÙˆÙ†ÙŠ Ø¨ÙƒØ°Ø¨Ø© Ø§Ù„Ù€ One Euro ÙˆØ§Ù„Ù€ 400 ÙƒÙ… ØªØ¨Ø¹Øª Ø¹Ù‚Ù„ Ø¨Ù„ØªØ§Ø¬ÙŠ... Ø·Ù„Ø¹Øª ÙˆÙ„Ø§ Ø§Ø´ÙŠ Ù…Ø¹ Ø§Ù„ÙƒØ°Ø¨ Ø§Ù„Ù„ÙŠ Ù‡ÙˆÙ† ... ÙˆØ§Ù„Ø§Ø­Ù„Ù‰ ÙƒÙŠÙ Ø§Ù„Ø±Ù‚Ù… ÙƒØ§Ù†... https://t.co/POVXY6nCWQ]]></document>
		<document><![CDATA[Ù‡Ø³Ø§ #ØªØ±Ø§Ù…Ø¨ Ø¨Ù‚Ø¯Ø± ÙŠØ­ÙƒÙŠ #Ù…ÙˆÙƒÙˆÙ„Ù‡ Ù…Ù† Ø§ÙˆÙ„ Ù…Ø±Ù‡ ...ØŸØŸ]]></document>
		<document><![CDATA[#Ù‡ÙŠÙ„Ø§Ø±ÙŠ_ÙƒÙ„ÙŠÙ†ØªÙˆÙ† ÙƒØ§ØªØ¨Ù‡ Ø¹ Ø¨Ø±ÙˆÙØ§ÙŠÙ„Ù‡Ø§ Ø¨Ø¹Ø¯ Ù…Ø§ Ø®Ø³Ø±Øª " Ù…Ø§ Ù†Ø­ØªØ§Ø¬ Ø±Ø¦Ø§Ø³Ù‡... Ù…Ù† Ø§Ù„Ù„Ù‡ Ø¯ÙˆÙ„Ù‡ " ...ðŸ˜‚]]></document>
		<document><![CDATA[Ù‚Ø§Ù„ Ù‚Ù„Ù‚Ø§Ù†ÙŠÙ† Ù…ÙŠÙ† ÙŠÙÙˆØ² #Ù‡ÙŠÙ„Ø§Ø±ÙŠ_ÙƒÙ„ÙŠÙ†ØªÙˆÙ† ÙˆÙ„Ø§ #ØªØ±Ø§Ù…Ø¨... ÙˆØ§Ù„Ø¬ÙˆØ² Ù…Ø«Ù„ #Ø§Ù„Ø®Ø¨Ø«_ÙˆØ§Ù„Ø®Ø¨Ø§Ø¦Ø« ...]]></document>
		<document><![CDATA[#Ø§Ù„Ø§Ø²Ù‡Ø±_Ø§Ù„Ø´Ø±ÙŠÙ : Ø®Ø·Ø¨Ù‡ Ø§Ù„Ø¬Ù…Ø¹Ù‡ ØºØ¯Ø§ Ø¹Ù† ÙØ¶Ù„ ØªØ¹ÙˆÙŠÙ… #Ø§Ù„Ø¬Ù†ÙŠÙ‡_Ø§Ù„Ù…ØµØ±ÙŠ ÙÙŠ Ø§Ù„Ø¥Ø³Ù„Ø§Ù…... !ðŸ˜‚]]></document>
		<document><![CDATA[#Ø§Ù„Ø³ÙŠØ³ÙŠ Ø¨Ù‚ÙˆÙ„ Ø£Ù†Ø§ Ù…Ù† Ø£Ø³Ø±Ø© ØºÙ†ÙŠØ© ÙˆÙ‚Ø¹Ø¯Øª 10 Ø³Ù†ÙŠÙ† Ø«Ù„Ø§Ø¬ØªÙŠ ÙÙŠÙ‡Ø§ Ù…ÙŠØ© Ø¨Ø³ ÙˆÙ…Ø­Ø¯Ø´ Ø³Ù…Ø¹ ØµÙˆØªÙŠ ...
ÙˆØ§Ù†Ø§ Ø¨Ù‚ÙˆÙ„ #Ø§Ù„Ù‚Ø°Ø§ÙÙŠ ÙÙƒØ±Ù‡ ...... https://t.co/YLI1FILbBw]]></document>
		<document><![CDATA[#Ø§Ù„Ø³ÙŠØ³ÙŠ Ø¨Ù‚ÙˆÙ„ : Ø§Ù†Ø§ Ù…ØµØ±ÙŠ Ø²ÙŠ Ø§Ù„Ù…ØµØ±ÙŠÙŠÙ† ÙˆØ«Ù„Ø§Ø¬ØªÙŠ 10 Ø³Ù†ÙŠÙ† ÙˆÙ…Ø§ÙÙŠÙ‡Ø§Ø´ ØºÙŠØ± Ø§Ù„Ù…ÙŽÙŠÙŽÙ‡ ÙˆÙ…Ø­Ø¯Ø´ Ø³Ù…Ø¹ ØµÙˆØªÙŠ ...
ÙˆØ§Ù†Ø§ Ø¨Ù‚ÙˆÙ„ #Ø§Ù„Ù‚Ø°Ø§ÙÙŠ... https://t.co/pVmlALFZsv]]></document>
		<document><![CDATA[#Ø§Ù„Ø³ÙŠØ³ÙŠ Ø¨Ù‚ÙˆÙ„ : Ø§Ù†Ø§ Ù…ØµØ±ÙŠ Ø²ÙŠ Ø§Ù„Ù…ØµØ±ÙŠÙŠÙ† ÙˆØ«Ù„Ø§Ø¬ØªÙŠ 10 Ø³Ù†ÙŠÙ† ÙˆÙ…Ø§ÙÙŠÙ‡Ø§Ø´ ØºÙŠØ± Ø§Ù„Ù…ÙŽÙŠÙŽÙ‡..
ÙˆØ§Ù†Ø§ÙˆØ¨Ù‚ÙˆÙ„ #Ø§Ù„Ù‚Ø°Ø§ÙÙŠ ÙÙƒØ±Ù‡ ... ÙˆØ§Ù„ÙÙƒØ±Ù‡ Ù„Ø§ ØªÙ…ÙˆØª..
Ù‡Ø§Ø´ØªØ§Ø§Ø§Øº #Ø«Ù„Ø§Ø¬Ù‡]]></document>
		<document><![CDATA[#Ø§Ù„Ù…ØªØ´Ø§Ø¦Ù… ÙŠØ±Ù‰ #Ø§Ù„Ø®Ø§Ø²ÙˆÙ‚ Ø¹Ù† Ø¨Ø¹Ø¯ Ø§Ù…Ø§ Ø§Ù„Ù…ØªÙØ§Ø¦Ù„ ÙÙ‡Ùˆ Ø§Ù„Ù„ÙŠ Ø¨ÙˆÙƒÙ„ Ø§Ù„Ø®Ø§Ø²ÙˆÙ‚ Ø¹Ù„Ù‰ Ø§Ù…Ù„ Ø§Ù†Ù‡ Ù…Ø§Ø±Ø§Ø­ ÙŠÙˆØ¬Ø¹...
#ØªÙ†Ù…ÙŠØ©_Ø¨Ø´Ø±ÙŠØ©]]></document>
		<document><![CDATA[#Ø§Ù„Ù…ØªØ´Ø§Ø¦Ù… ÙŠØ±Ù‰ #Ø§Ù„Ø®Ø§Ø²ÙˆÙ‚ Ø¹Ù† Ø¨Ø¹Ø¯ Ø§Ù…Ø§ Ø§Ù„Ù…ØªÙØ§Ø¦Ù„ ÙÙ‡Ùˆ Ø§Ù„Ù„ÙŠ Ø¨ÙˆÙƒÙ„ Ø§Ù„Ø®Ø§Ø²ÙˆÙ‚ Ø¹Ù„Ù‰ Ø§Ù…Ù„ Ø§Ù†Ù‡ Ù…Ø§Ø±Ø§Ø­ ÙŠÙˆØ¬Ø¹
#ØªÙ†Ù…ÙŠØ©_Ø¨Ø´Ø±ÙŠØ©]]></document>
		<document><![CDATA[ÙˆØµÙ„ Ø§Ù„Ø´ÙŠØ¨Ø³ Ø§Ù„Ø³ÙŠØ§Ø³ÙŠ Ù„Ù„Ù…Ø¯Ø§Ø±Ø³ ...!!!
#Ø§Ù†ØªØ®Ø§Ø¨Ø§Øª #Ù…Ø¬Ù„Ø³_Ø§Ù„Ø·Ù„Ø¨Ù‡ ÙÙŠ Ø§Ù„Ù…Ø¯Ø§Ø±Ø³ ... Ù…Ø¹Ù„ÙˆÙ…Ø§Øª Ø¹Ù† Ø´Ø±Ø§Ø¡ Ø§ØµÙˆØ§Øª ÙˆØ°Ù…Ù… ÙÙŠ Ø¹Ø¯ÙŠØ¯ Ù…Ù† Ø§Ù„Ù…Ø¯Ø§Ø±Ø³ ...]]></document>
		<document><![CDATA[Ø¯Ø¨ÙŠ Ø¨Ø¯Ù‡Ø§ ØªØ¨Ù†ÙŠ ÙƒÙ…Ø§Ù† Ø¨Ø±Ø¬ Ø§Ø·ÙˆÙ„ Ù…Ù† #Ø¨Ø±Ø¬_Ø®Ù„ÙŠÙÙ‡ ...ó¾€
Ø¨Ø³ Ø¨Ø±Ø¶Ùˆ Ù„Ø³Ø§ ÙÙŠØ´ Ø¹Ù†Ø¯Ù‡Ù… #Ø³Ø§Ù…Ø­_Ù…ÙˆÙ„ ÙˆÙ„Ø§ #Ø¨Ø§Øµ_Ø³Ø±ÙŠØ¹
#ÙŠØ§_Ø­Ø±Ø§Ù…]]></document>
		<document><![CDATA[Ø¯Ø¨ÙŠ Ø¨Ø¯Ù‡Ø§ ØªØ¨Ù†ÙŠ ÙƒÙ…Ø§Ù† Ø¨Ø±Ø¬ Ø§Ø·ÙˆÙ„ Ù…Ù† #Ø¨Ø±Ø¬_Ø®Ù„ÙŠÙÙ‡ ...ó¾€
Ø¨Ø³ Ø¨Ø±Ø¶Ùˆ Ù„Ø³Ø§ ÙÙŠØ´ Ø¹Ù†Ø¯Ù‡Ù… #Ø³Ø§Ù…Ø­_Ù…ÙˆÙ„
#ÙŠØ§_Ø­Ø±Ø§Ù…]]></document>
		<document><![CDATA[Ø§Ø³ØªÙ‚Ø¨Ø§Ù„ Ø±Ø¦ÙŠØ³ Ù‡ÙŠØ¦Ø© Ø§Ù„Ø§Ø±ÙƒØ§Ù† ÙÙŠ #Ø¹Ø¬Ù„ÙˆÙ† ... https://t.co/jlWYcXE0DL]]></document>
		<document><![CDATA[#ÙˆØ²ÙŠØ±_Ø§Ù„ØªØ±Ø¨ÙŠÙ‡_ÙˆØ§Ù„ØªØ¹Ù„ÙŠÙ… Ø²ÙŠ Ø§Ù„Ù„ÙŠ Ø¨ÙØ³Ø¯ Ø§Ù„ÙˆØ¶Ùˆ ØªØ¨Ø¹Ùˆ Ø¹Ù†Ø¯ Ø§Ù„ØªØ´Ù‡Ø¯ ... ØµÙ„Ù‰ ØµÙ„Ù‰ ØµÙ„Ù‰ ÙˆØ¨Ø¢Ø®Ø± Ø§Ù„ØµÙ„Ø§Ù‡ #Ø·Ù‚Ø¹ ** Ø®Ø±Ø¨ ÙÙŠÙ‡ ÙƒÙ„ Ø§Ø´ÙŠ ... !!!]]></document>
		<document><![CDATA[ØªØªØ´Ø±Ù Ø¹Ø´ÙŠØ±Ø© Ø§Ù„ÙØ±ÙŠØ­Ø§Øª Ø¯Ø§Ø®Ù„ Ø§Ù„Ù…Ù…Ù„ÙƒØ© ÙˆØ®Ø§Ø±Ø¬Ù‡Ø§ Ø¨Ø¹Ø¯Ø¹ÙˆØªÙƒÙ… Ù„Ø­Ø¶ÙˆØ± Ø­ÙÙ„ Ø§Ø³ØªÙ‚Ø¨Ø§Ù„ Ø±Ø¦ÙŠØ³ Ù‡ÙŠØ¦Ø© Ø§Ù„Ø£Ø±ÙƒØ§Ù† Ø§Ù„Ù…Ø´ØªØ±ÙƒØ© Ø§Ù„Ø¨Ø§Ø´Ø§ Ù…Ø­Ù…ÙˆØ¯... https://t.co/1kqbJaeX88]]></document>
		<document><![CDATA[Ø§Ù„Ø¨Ø§Ø´Ø§ Ø±Ø¦ÙŠØ³ Ù‡ÙŠØ¦Ø© Ø§Ù„Ø§Ø±ÙƒØ§Ù† Ø§Ù„Ù…Ø´ØªØ±ÙƒÙ‡ ... Ù…Ø­Ù…ÙˆØ¯ Ø¨Ø§Ø´Ø§ ÙØ±ÙŠØ­Ø§Øª ... https://t.co/VchQqP4Sjn]]></document>
		<document><![CDATA[Ù…Ø¨Ø±ÙˆÙƒ Ù„Ø§Ø¨Ù† Ø¬Ø±Ø´ ... Ø§Ù„ÙØ±ÙŠÙ‚ Ù…Ø­Ù…ÙˆØ¯ Ø¨Ø§Ø´Ø§ ÙØ±ÙŠØ­Ø§Øª Ù‚Ø§Ø¦Ø¯Ø§ Ù„Ù„Ø¬ÙŠØ´ ...]]></document>
		<document><![CDATA[Ø§Ù„ÙŠÙˆÙ… ÙˆØ§Ø­Ø¯ Ù…Ø§Ø´ÙŠ Ø¨Ø³ÙŠØ§Ø±ØªÙ‡ ÙˆÙ…Ø´ØºÙ„ Ø£ØºØ§Ù†ÙŠ ÙˆØ§Ù„ØµÙˆØª Ø¹Ø§Ù„ÙŠ Ø¹Ø§Ù„Ø¢Ø®Ø±  Ùˆ #Ø´Ù…Ø¹ÙˆÙ†_Ø¨ÙŠØ±ÙŠØ² Ù…Ø§ Ø§Ù„Ù‡ÙˆØ´ ÙŠÙˆÙ…ÙŠÙ† Ù…ØªÙˆÙÙŠ...
#Ø¹Ø§Ù„Ù…_Ø¨Ø·Ù„Øª_ØªØ³ØªØ­ÙŠ ...]]></document>
		<document><![CDATA[Ø¨Ù…Ù†Ø§Ø³Ø¨Ø© Ø­Ù„ÙˆÙ„ Ø§Ù„Ø³Ù†Ø© Ø§Ù„Ù‡Ø¬Ø±ÙŠØ© Ø§Ù„Ø¬Ø¯ÙŠØ¯Ø©... Ù†Ø¯Ø¹ÙˆÙ‡ Ø¹Ø² Ùˆ Ø¬Ù„ Ø§Ù† ØªÙƒÙˆÙ† Ø³Ù†Ø© Ù…Ø¨Ø§Ø±ÙƒØ© ÙˆØ³Ù†Ø© Ø®ÙŠØ± Ø¹Ù„ÙŠÙ†Ø§ Ø¬Ù…ÙŠØ¹Ø§ Ø§Ù† Ø´Ø§Ø¡ Ø§Ù„Ù„Ù‡ ...... https://t.co/3NrgaFFZMo]]></document>
		<document><![CDATA[Ù…Ù†ØªØ®Ø¨ Ø§Ù„Ø§Ø±Ø¯Ù† Ù„Ù„Ø³ÙŠØ¯Ø§Øª ØªØ­Øª 17 Ø¹Ø§Ù… ... #Ø§Ø®ØªØ§Ù‡_Ù…ÙƒØ§Ù†Ùƒ_Ø§Ù„Ù…Ø·Ø¨Ø®
#Ø§Ù„Ø§Ø±Ø¯Ù† Vs #Ø§Ø³Ø¨Ø§Ù†ÙŠØ§ 6:0 #ÙƒØ£Ø³_Ø§Ù„Ø¹Ø§Ù„Ù…_Ù„Ù„Ø³ÙŠØ¯Ø§Øª]]></document>
		<document><![CDATA[Ø­ØªÙ‰ Ù†ÙƒÙˆÙ† Ù…Ù†ØµÙÙŠÙ†...
Ø§Ù„Ù„ÙŠ Ù…Ù‡ØªÙ… Ø¨Ù‚Ø¶ÙŠØ© #ØªØ¹Ø¯ÙŠÙ„_Ø§Ù„Ù…Ù†Ø§Ù‡Ø¬ ÙŠØ­Ø· Ø¹ Ø§Ù„ØªÙ„ÙØ²ÙŠÙˆÙ† Ø§Ù„Ø§Ø±Ø¯Ù†ÙŠ ÙˆÙŠØ³Ù…Ø¹ ÙƒÙ„Ø§Ù… Ù„Ø¬Ù†Ø© Ø§Ù„ØªØ­Ù‚ÙŠÙ‚ ... Ø§Ù„Ù…ÙˆØ¶ÙˆØ¹ Ù„Ø§... https://t.co/nkJUB2G7pL]]></document>
		<document><![CDATA[Ù„Ùˆ ÙƒØ§Ù† ÙÙŠÙ‡ ÙˆØ²ÙŠØ± Ø¯ÙˆÙ„Ù‡ Ù„Ø´Ø¤ÙˆÙ† Ø§Ù„Ù†Ù‚Ù„ ÙƒØ§Ù† Ù…Ø§ ØµØ§Ø± Ø§Ù„Ù„ÙŠ ØµØ§Ø±...
#Ù…Ù†Ù‚ÙˆÙ„
#Ø§Ø³ØªÙ‚Ø§Ù„Ø©_ÙˆØ²ÙŠØ±_Ø§Ù„Ù†Ù‚Ù„]]></document>
		<document><![CDATA[Ù„Ùˆ ÙƒØ§Ù† ÙÙŠ ÙˆØ²ÙŠØ± Ø¯ÙˆÙ„Ù‡ Ù„Ø´Ø¤ÙˆÙ† Ø§Ù„Ù†Ù‚Ù„ ÙƒØ§Ù† Ù…Ø§ ØµØ§Ø± Ø§Ù„Ù„ÙŠ ØµØ§Ø±...
#Ù…Ù†Ù‚ÙˆÙ„]]></document>
		<document><![CDATA[Ø§Ù„ØªØ¹ÙŠÙŠÙ†Ø§Øª ÙˆÙŠÙ† Ù…Ø§ÙƒØ§Ù† Ø¨Ø¯Ù‡Ø§ ÙØ­Øµ ÙƒÙØ§Ø¡Ø© ... Ø§Ù„Ø§ Ø§Ù„Ù…Ù†Ø§ØµØ¨ Ø§Ù„Ø¹Ù„ÙŠØ§ Ø¨Ø¯Ù‡Ø§ ÙØ­Øµ DNA ... 
#Ø§Ù„ÙˆØ²ÙŠØ±_Ø¨ÙØ¬ÙØ±_ÙˆØ²ÙŠØ±_ÙˆØ§Ù„Ù‚Ù…Ù„_Ø¨ÙØ¬ÙØ±_ØµÙŠØ¨Ø§Ù†]]></document>
		<document><![CDATA[ÙŠØ¹ÙŠÙ† Ù…Ø¹Ø§Ù„ÙŠ Ø§Ù„Ø³ÙŠØ¯ Ù†Ø§ØµØ± Ø¬ÙˆØ¯Ø© Ù†Ø§Ø¦Ø¨Ø§ Ù„Ø±Ø¦ÙŠØ³ Ø§Ù„ÙˆØ²Ø±Ø§Ø¡ØŒ ÙˆÙˆØ²ÙŠØ±Ø§ Ù„Ù„Ø®Ø§Ø±Ø¬ÙŠØ©
ÙŠØ¹ÙŠÙ† Ù…Ø¹Ø§Ù„ÙŠ Ø§Ù„Ø¯ÙƒØªÙˆØ± Ø¨Ø´Ø± Ù‡Ø§Ù†ÙŠ Ø§Ù„Ø®ØµØ§ÙˆÙ†Ø© ÙˆØ²ÙŠØ± Ø¯ÙˆÙ„Ø©... https://t.co/0ZX8qH3i1J]]></document>
		<document><![CDATA[#Ù†Ø§ØµØ±_Ø¬ÙˆØ¯Ù‡ Ø§Ø®Ø° ÙˆØ²Ø§Ø±Ø© Ø§Ù„Ø®Ø§Ø±Ø¬ÙŠØ© 7 Ù…Ø±Ø§Øª Ùˆ #Ø¨Ø±Ø´Ù„ÙˆÙ†Ù‡ Ø§Ø®Ø° Ø§Ø¨Ø·Ø§Ù„ Ø§ÙˆØ±ÙˆØ¨Ø§ 5 Ù…Ø±Ø§Øª Ù„Ù„Ø¹Ù„Ù… ØªØ£Ø³Ø³ Ø§Ù„Ù†Ø§Ø¯ÙŠ ÙÙŠ. 1899....]]></document>
		<document><![CDATA[Ù…Ø´ Ù…Ù‡Ù… #Ø§Ù„ØºØ§Ø² ÙŠÙƒÙˆÙ† Ù…Ù† ÙˆÙŠÙ† ... Ø§Ù„Ù…Ù‡Ù… #Ø§Ù„Ø¬Ù„Ø¯Ù‡ ØªÙƒÙˆÙ† ØµÙ†Ø§Ø¹Ù‡ #ÙˆØ·Ù†ÙŠÙ‡ ...]]></document>
		<document><![CDATA[#ØºØ§Ø²_Ø§Ù„Ø¹Ø¯Ùˆ_Ø§Ø­ØªÙ„Ø§Ù„ ( Ø¨Ø§Ù„Ø¹Ø¨Ø±ÙŠ) ...]]></document>
		<document><![CDATA[#ØºØ§Ø²_Ø§Ù„Ø¹Ø¯Ùˆ_Ø§Ø­ØªÙ„Ø§Ù„ ( Ø¨Ø§Ù„Ø¹Ø¨Ø±ÙŠ) ... ðŸš†]]></document>
		<document><![CDATA[Ù…Ø§ ÙÙŠ Ø§Ø´ÙŠ Ø¨Ø§Ù„Ø§Ø³Ù„Ø§Ù… ÙŠÙØ±Ø¶ Ø§Ù„Ù‚ØªÙ„ Ø¹Ù„Ù‰ Ø§Ù„Ù…Ø³ØªÙ‡Ø²Ø¦ Ø¨Ø§Ù„Ø¯ÙŠÙ† Ù…Ø«Ù„ #Ù†Ø§Ù‡Ø¶_Ø­ØªØ± ...
(ÙˆÙŽÙ‚ÙŽØ¯Ù’ Ù†ÙŽØ²ÙŽÙ‘Ù„ÙŽ Ø¹ÙŽÙ„ÙŽÙŠÙ’ÙƒÙÙ…Ù’ ÙÙÙŠ Ø§Ù„Ù’ÙƒÙØªÙŽØ§Ø¨Ù... https://t.co/Z1lbGXaDgh]]></document>
		<document><![CDATA[#Ø¥ØºØªÙŠØ§Ù„_Ù†Ø§Ù‡Ø¶_Ø­ØªØ±
ØµØ­ÙŠÙØ© Ø§Ù„ØºØ¯ : Ù‚Ø§ØªÙ„ Ù†Ø§Ù‡Ø¶ Ø­ØªØ± Ø¯Ø®Ù„ Ø§Ù„Ø£Ø±Ø¯Ù† ÙŠÙˆÙ… Ø£Ù…Ø³ Ù‚Ø§Ø¯Ù…Ø§Ù‹ Ù…Ù† Ø¨Ù„Ø¯ Ù…Ø¬Ø§ÙˆØ± .]]></document>
		<document><![CDATA[Ù…Ø´ Ø§Ù„Ù‚Ø§Ù†ÙˆÙ† Ø¨Ø³Ø¬Ù† Ø§Ù„Ø¹Ø±ÙŠØ³ Ø§Ù„Ù„ÙŠ Ø¨Ù†Ø·Ø® Ø¨Ø¹Ø±Ø³Ùˆ..ØŸØŸ
Ù…Ø´ Ø§Ù„Ø§Ù†ØªØ®Ø§Ø¨Ø§Øª #Ø¹Ø±Ø³_ÙˆØ·Ù†ÙŠ ØŸØŸØŸ
Ù…Ø´ ÙŠØ­ÙŠÙ‰ Ø³Ø¹ÙˆØ¯ Ø¹Ø±ÙŠØ³ Ù…Ù† Ù‡Ø§Ù„Ø¹Ø±Ø³Ø§Ù† ØŸØŸØŸ #Ø§Ø³Ø¬Ù†ÙˆÙ‡ Ù†Ø´ÙˆÙ]]></document>
		<document><![CDATA[Ù‡Ø³Ø§ Ø¨ÙƒÙˆÙ†Ùˆ Ø¨ØºÙ†Ùˆ Ù„Ù€ #Ø²ÙŠÙ†_ÙƒØ±Ø²ÙˆÙ† Ø¨Ø§Ù„Ø³Ø¬Ù†
Ø§Ø¬Ø¬Øª Ø¹Ù†Ø§Ø§Ø§Ø§ Ø²ÙŠÙŠÙŠØ²Ùˆ ... ó¾Œ´ó¾Œ´]]></document>
		<document><![CDATA[Ø§Ù„Ø§Ù…Ù† ÙŠÙˆÙ‚Ù #Ø²ÙŠÙ†_ÙƒØ±Ø²ÙˆÙ† ÙÙŠ Ø§Ù„Ù…Ø·Ø§Ø± Ø¹Ù„Ù‰ Ù‚Ø¶Ø§ÙŠØ§ Ù‚Ø¯Ø­ ÙˆØ°Ù… Ø¨Ø¹Ø¯ ÙˆØµÙÙ‡Ø§ Ù„Ù„Ø§Ø±Ø¯Ù†ÙŠÙ† Ø¨Ø§Ù„ØµØ±Ø§ØµÙŠØ±...
Ù‡Ø§Ø´ØªØ§Ø§Ø§Øº #ÙˆØ§Ù„Ù„Ù‡_ÙˆØ±Ø®ØµØª_ÙŠØ§_ÙØ¬Ù„ #Ù‡ÙŠ_Ù„Ø­Ù…Ø§Ø§Ø§Ø§Øª_ÙÙŠÙÙˆÙˆÙˆ]]></document>
		<document><![CDATA[ÙÙŠØ¯ÙŠÙˆ ÙŠÙˆØ«Ù‚ Ø±Ø¤ÙŠØ§ Ø§Ù„Ù…Ø±Ø´Ø­ Ø§Ù„Ù…Ù‚Ø§Ø¨Ù„Ù‡ Ø§Ù„Ø°ÙŠ Ø¬Ø§Ø¡Ù‡ Ù…Ø±Ø³Ù„ Ù„ØªØ¨Ø´ÙŠØ±Ù‡ Ø¨Ø§Ù„Ù†Ø¬Ø§Ø­ Ø¨Ø§Ù„Ø§Ù†ØªØ®Ø§Ø¨Ø§Øª
Ù‡Ùˆ Ø¬Ø§Ø¨ 1000 ØµÙˆØª Ø¨ØµÙ†Ø§Ø¯ÙŠÙ‚ Ø§Ù„Ø§Ø±Ø¶ ÙˆØ¶Ø§ÙŠÙ„... https://t.co/xgESqa7mhi]]></document>
		<document><![CDATA[Ø´Ø±ÙŠØ· ÙÙŠØ¯ÙŠÙˆ ÙŠÙˆØ«Ù‚ Ø±Ø¤ÙŠØ§ Ø§Ù„Ù…Ø±Ø´Ø­ Ø§Ù„Ù…Ù‚Ø§Ø¨Ù„Ù‡ Ø§Ù„Ø°ÙŠ Ø¬Ø§Ø¡Ù‡ Ù…Ø±Ø³Ù„ Ù„ØªØ¨Ø´ÙŠØ±Ù‡ Ø¨Ø§Ù„Ù†Ø¬Ø§Ø­ Ø¨Ø§Ù„Ø§Ù†ØªØ®Ø§Ø¨Ø§Øª ...ó¾Œ´ó¾Œ´
Ù‡Ùˆ Ø¬Ø§Ø¨ 1000 ØµÙˆØª Ø¨ØµÙ†Ø§Ø¯ÙŠÙ‚... https://t.co/4AbYk4BqNu]]></document>
		<document><![CDATA[Ø§Ø¬Ù…Ù„ Ù…Ø§ ÙÙŠ Ø§Ù„Ø§Ù†ØªØ®Ø§Ø¨Ø§Øª Ø§Ù†Ù‡Ø§ Ø§Ø³Ù‚Ø·Øª Ø§ØµÙ†Ø§Ù… Ø§Ù„Ù…Ø¬Ù„Ø³ Ù…Ù† Ø§ÙŠØ§Ù… Ø§Ù„Ø¬Ø§Ù‡Ù„ÙŠÙŠÙ‡ Ù…Ø«Ù„ Ø§Ù„Ø®Ø±Ø§Ø¨Ø´Ù‡ ÙˆØ§Ù„Ø±Ø­ÙŠÙ…ÙŠ ÙˆØ³Ø¹Ø¯ Ù‡Ø§ÙŠÙ„ Ø³Ø±ÙˆØ± ÙˆØºÙŠØ±Ù‡Ù… ...... https://t.co/W7sIlQrubh]]></document>
		<document><![CDATA[ÙˆÙ„Ø§ ÙƒØ£Ù†Ùˆ Ø«Ø§Ù†ÙŠ ÙŠÙˆÙ… #Ø§Ù†ØªØ®Ø§Ø¨Ø§Øª ... ó¾Œ¦]]></document>
		<document><![CDATA[Ø³Ù†Ù‡ Ù„Ù€ #Ù…ÙƒÙ‡ ÙˆØ³Ù†Ù‡ Ù„Ù€ #Ù…ÙƒÙ‡_Ù…ÙˆÙ„
#Ø¨Ø«ÙŠÙ†Ù‡_Ø§Ù„Ø·Ø±Ø§ÙˆÙ†Ù‡... Ø§Ù„Ø§Ù†ØªØ®Ø§Ø¨Ø§Øª Ø§Ù„Ù…Ø§Ø¶ÙŠÙ‡ ØªØ±Ø´Ø­Øª Ù…Ø¹ Ù†Ù‚Ø§Ø¨Ø© Ø§Ù„Ù…Ù‡Ù†Ø¯Ø³ÙŠÙ† Ø§Ù„Ù…Ø­ÙƒÙˆÙ…Ù‡ Ù…Ù† #Ø§Ù„Ø§Ø®ÙˆØ§Ù†... https://t.co/jYFuA6nw8j]]></document>
		<document><![CDATA[Ø§Ù„Ù…Ø±Ø´Ø­ #Ù†Ø¬Ù…_Ø§Ù„Ø¯ÙŠÙ†_Ø§Ù„Ø·ÙˆØ§Ù„Ø¨Ø© Ø§Ùˆ #ØªØ§Ø¬Ø±_Ø§Ù„Ø¯ÙŠÙ†_Ø§Ù„Ø·ÙˆØ§Ù„Ø¨Ù‡
"Ø§Ù„ØªØ²ÙˆØ¯ Ø¨Ø¨Ø±ÙƒØ§Øª #Ø§Ù„ØµØ±ÙŠØ­ ÙŠØ³Ù‚Ø· Ø¹Ù†ÙŠ ÙØ±Ø¶ #Ø§Ù„Ø­Ø¬ Ù…Ø¬Ø§Ø²Ø§" Ùˆ " Ø§Ù„ØµØ±ÙŠØ­... https://t.co/BcyIArv1tN]]></document>
		<document><![CDATA[ÙŠØ§ Ù…Ø±Ø´Ø­ Ù„Ø§ ØªÙ‚ØµØµ Ø±Ø¤ÙŠØ§Ùƒ Ø¹Ù„Ù‰ Ø§Ø¹Ø¶Ø§Ø¡ Ù‚Ø§Ø¦Ù…ØªÙƒ ÙÙŠÙƒÙŠØ¯Ùˆ Ù„Ùƒ ÙƒÙŠØ¯Ø§...
#Ù…Ø­Ù…Ø¯_Ù†ÙˆØ­_style
Ø¹ÙŠÙ†Ù‡ Ù…Ù† Ø®Ø·Ø§Ø¨Ø§Øª Ø§Ù„Ù…Ø±Ø´Ø­ÙŠÙ† ÙÙŠ #Ø¬Ø±Ø´ Ùˆ #Ø§Ù„Ø²Ø±Ù‚Ø§Ø¡... ó¾„â˜]]></document>
		<document><![CDATA[Ø§ÙˆÙ„ Ø±Ø¯ ÙØ¹Ù„ Ù…Ù† ÙˆØ²Ø§Ø±Ø© Ø§Ù„Ø®Ø§Ø±Ø¬ÙŠÙ‡ Ø¹Ù„Ù‰ Ø§Ø³ØªØ´Ù‡Ø§Ø¯ Ø§Ù„Ø§Ø±Ø¯Ù†ÙŠ #Ø³Ø¹ÙŠØ¯_Ø§Ù„Ø¹Ù…Ø±Ùˆ ÙÙŠ #Ø§Ù„Ù‚Ø¯Ø³ Ø§Ù„ÙŠÙˆÙ…:
Ù†Ø§ØµØ± Ø¬ÙˆØ¯Ù‡ Ø¹Ø§Ù…Ù„ ÙÙˆÙ„Ùˆ #follow Ù„ØµÙØ­Ø©... https://t.co/Zv4euPGsOP]]></document>
		<document><![CDATA[Ù‚Ø§Ù„ #Ø¯ÙˆÙ„Ù‡_Ù…Ø¯Ù†ÙŠÙ‡ Ù‚Ø§Ù„...!!! #Ù‚Ø§Ø¦Ù…Ø©_Ù…Ø¹Ø§ #Ù‚ÙŠØ³_Ø²ÙŠØ§Ø¯ÙŠÙ†
Ø¹ Ø³ÙŠØ±Ø© Ø§Ù„Ø§Ù„Ø­Ø§Ø¯... ÙˆØ§Ø­Ø¯ Ù…Ù„Ø­Ø¯ Ø±Ø§Ø­ ÙŠØ¹Ø²ÙŠ ØµØ§Ø­Ø¨Ù‡ Ø¹Ø´Ø§Ù† ØªÙˆÙÙ‰ Ø§Ø¨ÙˆÙ‡... Ù…Ø§... https://t.co/SQdr4xHHbJ]]></document>
		<document><![CDATA[ÙƒØ¨Ø±Ù†Ø§ Ø¹ Ø§Ù„Ø¹ÙŠØ¯ÙŠØ§Øª... ØµØ§Ø± Ø¨Ø¯Ù†Ø§ Ù‚Ø±ÙˆØ¶... ó¾€âœ‹]]></document>
	</documents>
</author>