<author lang="ar">
	<documents>
		<document><![CDATA[Ùˆ Ø§Ù‡Ø¬Ø±Ù‡ÙÙ… Ù‡Ø¬Ø±Ø§ Ø¬Ù…ÙŠÙ„Ø§Ù‹..
Ø£Ø¯Ø¨ Ø§Ù„Ù‚Ø±Ø¢Ù† Ù„Ø§ ÙŠØ¹Ù„Ù…Ùƒ Ø£Ù† ØªØ£Ø®Ø° Ø§Ù„ØµØ±Ø§Ø® Ø¨Ù€ Ø§Ù„ØµØ±Ø§Ø®
 Ùˆ Ù„Ø§ Ø§Ù„Ø´ØªÙ… Ø¨Ù€Ø§Ù„Ø´ØªÙ… 
Ø¹ÙØ´ Ø¬Ù…Ø§Ù„ Ø§Ù„Ø­ÙŠØ§Ø© 
ÙÙŠ Ø§Ù„Ø¥Ø¹Ø±Ø§Ø¶ Ø¹Ù† Ù‡Ø°Ù‡ Ø§Ù„ÙØ¦Ø© Ù…Ù† Ø§Ù„Ø¨Ø´Ø±.]]></document>
		<document><![CDATA[Ø£Ø­Ø³ Ø¨Ø£Ø®ØªÙ†Ø§Ù‚ ØºÙŠØ± Ø¹Ù† ÙƒÙ„ Ù…Ø±Ø©ðŸ’­]]></document>
		<document><![CDATA[@sarounaxx Ø¨Ø§Ù„Ø³Ù„Ø§Ù…Ù‡ Ø­Ø¨ÙŠØ¨ÙŠ ØŒ ØªØ­Ù…Ù„ÙŠ Ø¨Ø±ÙˆØ­Ø¬â¤ï¸ðŸ˜˜]]></document>
		<document><![CDATA[Ù…Ù‡Ù…Ø§ ÙƒØ§Ù†Øª Ù…ÙƒØ§Ù†ØªÙƒ Ø¹Ù†Ø¯ÙŠ Ø§Ù‚Ø¯Ø± Ø§Ø³ØªØºÙ†Ù‰ Ø¹Ù†Ùƒ ÙØ§Ù„Ø«Ø§Ù†ÙŠÙ‡ Ø§Ù„Ù„ÙŠ ØªØ³ØªØºÙÙ„Ù†ÙŠ ÙÙŠÙ‡Ø§.]]></document>
		<document><![CDATA[ÙØ§Ù‚Ø¯ Ø§Ù„Ø³Ø¹Ø§Ø¯Ø© ÙŠÙ…Ù„Ùƒ ØºØ§Ù„Ø¨Ø§Ù‹ Ù‚Ø¯Ø±Ø© Ù‡Ø§Ø¦Ù„Ø© Ø¹Ù„Ù‰ Ù†Ø´Ø± Ø§Ù„Ø³Ø¹Ø§Ø¯Ø© Ù„Ù…Ù† Ø­ÙˆÙ„Ù‡.]]></document>
		<document><![CDATA[Ø±Ø³Ø§Ù„Ù‡ ØµØ¨Ø§Ø­ÙŠÙ‡ : 
Ù„Ø§ ØªÙ‚ØªÙ„ ØµØ¨Ø§Ø­Ùƒ Ø¨Ø£ÙÙƒØ§Ø±Ø§Ù„Ø£Ù…Ø³ Ø«Ù‚ Ø¨Ø£Ù† Ù„ÙƒÙ„ ÙŠÙˆÙ… Ø£Ø´ÙŠØ§Ø¡ Ø£Ø¬Ù…Ù„ .]]></document>
		<document><![CDATA[Ù‡Ù†Ø§Ùƒ Ù…Ù† ÙŠÙ‡Ø¯ÙŠÙƒ Ø§Ù„Ø­Ø¨ ÙˆØ§Ù„ÙˆÙØ§Ø¡ ..
Ø¯ÙˆÙ† Ø£Ù† ØªÙ‡Ø¯ÙŠÙ‡ Ø£ÙŠ Ø´ÙŠ ..
ÙˆÙ‡Ù†Ø§Ùƒ Ù…Ù† ÙŠÙ‡Ø¯ÙŠÙƒ Ø§Ù„Ø£Ù„Ù… ..
Ø¨Ø¹Ø¯ Ø£Ù† ØªÙ‡Ø¯ÙŠÙ‡ ÙƒÙ„ Ø´ÙŠ .]]></document>
		<document><![CDATA[Ø§Ù„Ù„Ù‡Ù… Ø¥Ù† Ø¹ÙŠÙ†ÙŠ Ø¥Ø´ØªØ§Ù‚Øª Ù„Ø±Ø¤ÙŠØªÙ‡Ø§ØŒ ÙˆØ£Ø°Ø¢Ù†ÙŠ Ø­Ù†Øª Ù„Ø³Ù…Ø§Ø¹ ØµÙˆØªÙ‡Ø§ØŒØ±Ø¨ÙŠ Ø¥Ù†Ù‡Ø§ Ø£ØºÙ„Ù‰ Ù…Ø§ÙÙ‚Ø¯Øª ÙØ§ÙƒØªØ¨ Ù„Ù†Ø§ Ù„Ù‚Ø§Ø¡ ÙÙŠ Ø¬Ù†ØªÙƒ Ø§Ù„Ù„Ù‡Ù… Ø§Ø±Ø­Ù…Ù‡Ø§ ÙˆØ§ØºÙØ±Ù„Ù‡Ø§ ÙˆØ§Ø¬Ø¹Ù„ Ø§Ù„Ø¬Ù†Ø© Ø¯Ø§Ø±Ù‡Ø§]]></document>
		<document><![CDATA[Ø¨Ø¹Ø¶ Ø§Ù„Ø¯Ø±ÙˆØ³..
ØªØ£ØªÙŠ ÙƒØµÙØ¹Ø§Øª Ù…Ø¤Ù„Ù…Ø©.. ÙˆÙ„ÙƒÙ† ï»» Ø¨Ø£Ø³.. Ù†ØªØ£Ù„Ù… Ù„Ù†ØªØ¹Ù„Ù….]]></document>
		<document><![CDATA[@deviloo2 Ø°ÙˆØ±Ø±Ø± Ø¨Ù†Øª Ø§Ù„Ø®Ø§Ù„Ù‡ ðŸ‘ðŸ»ðŸ˜‚]]></document>
		<document><![CDATA[Ø¹Ø´ ÙƒÙ…Ø§ Ø´Ø¦Øª ÙØ£Ù†Øª Ø¹Ø§Ø¦Ø¯ ÙƒÙ…Ø§ Ø¬Ø¦Øª ."]]></document>
		<document><![CDATA[Ø§ÙƒØ¨Ø± ØºÙ„Ø· ØªØ³ÙˆÙŠÙ‡ ØªØ¹Ù„Ù… Ø£Ù‡Ù„Ùƒ Ù…ØªÙ‰ Ø£Ø®ØªØ¨Ø§Ø±Ø§ØªÙƒØŒ Ù„Ùˆ ØªØ¹Ø·Ø³ Ù‚Ø§Ù„ÙˆØ§ Ù‡Ø°Ø§ Ø§Ù„Ù„ÙŠ Ø¹Ù„ÙŠÙ‡ Ø£Ø®ØªØ¨Ø§Ø±ðŸ™‚]]></document>
		<document><![CDATA[Ø«Ù… ÙŠØ±Ø¶ÙŠÙƒ Ø§Ù„Ù„Ù‡ ÙˆÙŠØ±Ø¶ÙŠÙƒ ÙˆÙŠØ±Ø¶ÙŠÙƒ
ÙˆÙŠÙ…Ù„Ø£Ùƒ Ø¨Ø§Ù„Ø±Ø¶Ø§ Ø­ØªÙ‰ ØªØ¸Ù† Ø£Ù†Ùƒ Ù„Ù… ØªØ­Ø²Ù† ÙŠÙˆÙ…Ù‹Ø§ðŸ’•]]></document>
		<document><![CDATA[Ø±Ø¨ÙŠ Ø¬Ù…Ù„Ù†ÙŠ Ø¨Ù†ÙØ³Ù ØµØ¨ÙˆØ±Ù‡ ØªØ´ÙƒØ±Ùƒ ÙƒÙ„Ù…Ø§ Ø¶Ø§Ù‚Øª Ø¨Ù‡Ø§ Ø§Ù„Ø·Ø±Ù‚]]></document>
		<document><![CDATA[Ø´Ø¨Ù„ Ù‡Ø§Ø´Ù… Ø¨Ø±Ø² Ù„ÙŠÙ‡Ù… 
Ù‡Ù„Ø§ Ø¨Ø³ÙŠÙ Ø§Ù„Ù‡ÙˆØ§Ø´Ù…
Ø³Ø¤Ø§Ù„ Ø§Ù„ÙƒÙ„ ØµÙÙ‰ ÙˆØ§Ø­Ø¯
Ø¹Ù„ÙŠ Ù„Ùˆ Ù‡Ø°Ø§ Ø¬Ø§Ø³Ù… ØŸ!
#Ø§Ù„Ù‚Ø§Ø³Ù… ðŸ’”]]></document>
		<document><![CDATA[Ø£Ø±Ø£ÙŠØªÙŽ Ø¥Ø° Ø¬ÙŽÙ†ÙŽÙ‘ Ø§Ù„Ù„ÙŠÙ„
ÙˆØ£ÙÙØ±ÙØºÙŽØª Ø§Ù„Ø£Ø±Ø¶Ù Ù…Ù† Ø§Ù„Ø¶Ø¬ÙŠØ¬ 
ÙƒÙŠÙ ÙŠÙÙ…Ø´Ø· ØµØ¯Ø±ÙŠ Ø§Ù„ØªÙˆÙ‚ 
Ùˆ ÙŠÙ„ØªÙÙ Ø¹Ù„Ù‰ Ø£Ù†ÙØ§Ø³ÙŠ Ø§Ù„Ø¶ÙŠÙ‚ØŸ https://t.co/nQBvjXIxLE]]></document>
		<document><![CDATA[Ø£Ø±Ø£ÙŠØªÙŽ Ø¥Ø° Ø¬ÙŽÙ†ÙŽÙ‘ Ø§Ù„Ù„ÙŠÙ„
ÙˆØ£ÙÙØ±ÙØºÙŽØª Ø§Ù„Ø£Ø±Ø¶Ù Ù…Ù† Ø§Ù„Ø¶Ø¬ÙŠØ¬ 
ÙƒÙŠÙ ÙŠÙÙ…Ø´Ø· ØµØ¯Ø±ÙŠ Ø§Ù„ØªÙˆÙ‚ 
Ùˆ ÙŠÙ„ØªÙÙ Ø¹Ù„Ù‰ Ø£Ù†ÙØ§Ø³ÙŠ Ø§Ù„Ø¶ÙŠÙ‚ØŸ]]></document>
		<document><![CDATA[ÙŠØ§Ù…Ù‰ Ø¨Ø¢Ø³Ù…Ùƒ Ø±Ø¯Ø¯Øª Ùˆ ÙŠØ§Ù…Ù‰ Ø¥Ø¹ÙŠØ¯ØŒ ÙŠÙ„ÙŠ Ø±Ù…Ø´Ùƒ Ù‚Ù„Ø¹ØªÙŠ Ùˆ Ø­Ø±Ø§Ø³ÙŠ ðŸ’•]]></document>
		<document><![CDATA[ØªØ¹Ø¨Øª Ø­Ø±ÙˆÙÙŠ Ùˆ ØªØ¹Ø¨ Ø³Ø§Ø¹ÙŠ Ø§Ù„Ø¨Ø±ÙŠØ¯ ØŒÙˆØ§Ù†Øª Ø­Ø¨Ùƒ ØµØ­Ø¨ØªÙŠ Ùˆ Ø¬Ù„Ø§Ø³ÙŠ Ø¹Ù„Ù‰ Ø§Ù„Ù‡Ø§Ù…Ø´ Ø¹Ø§ÙŠØ´ ÙˆÙŠØ§Ùƒ Ùˆ Ø³Ø¹ÙŠØ¯ ..âœ¨]]></document>
		<document><![CDATA[Ø¬Ø¨Ù„ Ø­Ø¨Ùƒ ÙÙˆÙ‚ Ù‚Ù„Ø¨ÙŠ Ø±Ø§Ø³ÙŠ Ø§Ù†Ø§ Ø¨ÙŠÙƒ ØªÙˆØ­Ø¯Øª ÙˆØ§Ù†Øª Ø§Ù„ÙˆØ­ÙŠØ¯ Ù…Ù† Ø§Ø´Ù… Ø¹Ø·Ø±Ùƒ ØªØ·ÙŠØ¨ Ø§Ù†ÙØ§Ø³ÙŠâœ¨ðŸ’ž]]></document>
		<document><![CDATA[Ø³Ø§Ù„ÙÙ‡ Ø§Ù†ÙŠ Ø§Ø­Ø§ÙØ¸ Ø¹Ù„Ù‰ Ø§Ù†ÙˆØ«ØªÙŠ ÙˆØ§Ù†Ø§ Ù…Ø¹ØµØ¨Ù‡ Ø§Ù†Ø³ÙˆÙ‡Ø§ Ø­ØªÙ‰ Ø§Ù„ÙˆÙ‚ÙÙ‡ ØªØªØºÙŠØ±ðŸ¤˜ðŸ¾ðŸ™„]]></document>
		<document><![CDATA[ÙƒÙ„Ø§Ù…ÙŠ ÙˆÙ‚Øª Ø§Ù„ØºÙŠØ±Ù‡ ÙˆØ§Ù„Ø²Ø¹Ù„ ÙˆØ§Ù„Ø¹ØµØ¨ÙŠÙ‡ Ù…Ø§ Ø§Ø¹Ø±ÙÙ‡ ÙˆÙ„Ø§ ÙŠØ¹Ø±ÙÙ†ÙŠ ÙˆÙ„Ø§ Ù„ÙŠ Ø®Øµ ÙÙŠÙ‡ðŸ˜ŠðŸ˜‚!!]]></document>
		<document><![CDATA[Ø¥Ø¨ØªØ³Ø§Ù…Ø© Ø§Ù„Ø£Ù… ØŒ ØªÙ†Ø³ÙŠÙƒ Ø¹Ø«Ø±Ø§Øª Ø§Ù„Ø­ÙŠØ§Ø©.]]></document>
		<document><![CDATA[ÙˆÙ„Ø£Ù†Ù‡Ø§ Ø£Ù…ÙŠ ÙŠØ§ Ø§Ù„Ù„Ù‡..Ù„Ø£Ù†Ù‡Ø§ Ø§Ù„Ø­ÙŠØ§Ø© ÙˆØ§Ù„ÙØ±Ø­ ÙˆØ§Ù„Ø·Ø±ÙŠÙ‚ Ø§Ù„Ù…ÙØ³ØªÙ‚ÙŠÙ… Ø§Ù„Ø°ÙŠ Ù„Ø§ ÙŠÙ†ØªÙ‡ÙŠ Ø¥Ù„Ø§ Ø¨Ø§Ù„Ø¥Ø·Ù…Ø¦Ù†Ø§Ù†ØŒØ§Ø­ÙØ¸Ù‡Ø§ Ù„ÙŠ.ðŸ’™]]></document>
		<document><![CDATA[Ø¥Ø°Ø§ ÙˆØµÙ„ØªÙƒ ÙØ¶ÙŠØ­Ø© Ù„Ø£Ø­Ø¯Ù‡Ù… ÙØ£Ø¬Ø¹Ù„Ù‡Ø§ ØªÙ‚Ù Ø¹Ù†Ø¯Ùƒ ÙØ¥Ù† ÙˆÙ‚ÙØª Ø¹Ù†Ø¯Ùƒ Ø£Ø®Ø°Øª Ø£Ø¬Ø± Ø§Ù„Ø³ØªØ± ÙˆÙ…Ù† Ø³ØªØ± Ù…Ø³Ù„Ù…Ø¢ Ø³ØªØ±Ù‡ Ø§Ù„Ù„Ù‡]]></document>
		<document><![CDATA[ÙˆÙ„Ù… ÙŠØ¹Ù„Ù… Ø£Ø­Ø¯ ÙƒÙ… Ù…Ø±Ø© Ù…Ø§Øª Ù‚Ù„Ø¨Ùƒ Ø«Ù… Ø£Ø­ÙŠØ§Ù‡Ù Ø§Ù„Ù„Ù‡ Ø¨Ù†ÙˆØ±Ù‡ØŒ ÙÙ‚Ø· Ø§Ù„Ù„Ù‡Ù ÙˆØ­Ø¯Ù‡ ÙŠØ¹Ù„Ù… Ø°Ù„Ùƒ.]]></document>
		<document><![CDATA[ÙŠØ§ Ø±Ø¨ Ø¨Ø¯Ù‘Ù„ ØªØ¹Ø¨Ù†Ø§ Ø¨Ø±Ø§Ø­Ù‡ Ùˆ Ù‡Ù…Ù‘Ù†Ø§ Ø¨ÙØ±Ø¬ Ùˆ Ù…Ø±ÙŠØ¶Ù†Ø§ Ø¨Ø´ÙØ§Ø¡ ØŒ ÙŠØ§ Ø±Ø¨ Ø§Ø¬Ø¨ Ø¯Ø¹ÙˆØ© ØªØºÙŠÙ‘Ø± Ø­Ø§Ù„Ù†Ø§ Ù„Ø§Ø­Ø³Ù†Ù‡ .]]></document>
		<document><![CDATA[Ø±Ø¨ÙŠ Ø¥Ù† ÙÙŠ Ù‚Ù„Ø¨ÙŠ Ø£Ù…ÙˆØ± Ù„Ø§ÙŠØ¹Ø±ÙÙ‡Ø§ Ø³ÙˆØ§ÙƒØŒ ÙØ­Ù‚Ù‚Ù‡Ø§ Ù„ÙŠ ÙŠØ§Ø§Ø±Ø­ÙŠÙ…. ðŸ™ðŸ»]]></document>
		<document><![CDATA[ØªØ°ÙƒÙ‘Ø± Ø¯Ø§Ø¦Ù…Ø§ : Ù„Ù‚Ø¯ Ø¹Ø²Ùƒ Ø§Ù„Ù„Ù‡ Ø¹Ù† ÙƒÙ„ Ø´Ø®Øµ Ù„Ø§ ÙŠÙ„ÙŠÙ‚ Ø¨ØµÙØ§ÙˆØªÙƒ ÙØ£Ø¨Ø¹Ø¯Ù‡Ù… Ø¹Ù†Ùƒ.]]></document>
		<document><![CDATA[Ø£Ù†Ø§ Ø¥Ù†Ø³ÙŽØ§Ù† Ù…ØºØ±Ù… Ø¨Ø§Ù„Ø¨Ø³ÙŽØ§Ø·Ø© Ù„Ù„Ø­Ø¯ Ø§Ù„ØºÙŠØ± Ù…Ù’Ø¹Ù‚ÙˆÙ„ØŒØ§Ù„ØªÙØ§ØµÙŠÙ„ Ø§Ù„ØµØºÙŠØ±Ø© Ù‡ÙŠÙŽÙ‘Ø§ Ø§Ù„Ù„ÙŠ ØªØ¹Ø·ÙŠ Ø§Ù„Ø¬Ù…ÙŽØ§Ù„ ÙØ¹Ù„Ø§Ù‹ØŒÙ‡ÙŠ Ø§Ù„Ù…Ø¹Ù†ÙŽÙ‰ Ø§Ù„Ø­Ù‚ÙŠÙ‚ÙÙŠ.]]></document>
		<document><![CDATA[Ø§Ø­Ù„Ù‰ Ø´ÙŠ Ø¥Ù†Ùƒ ØªØ¹Ø±Ù ÙƒÙ„ Ø´ÙŠ ÙˆØªØ³ÙˆÙŠ Ø±ÙˆØ­Ùƒ ØºØ¨ÙŠðŸ˜‚.]]></document>
		<document><![CDATA[Ø¨Ø¹Ø¶ Ø§Ù„Ø¹Ù‚ÙˆÙ„ Ù‡Ø¯ÙÙ‡Ø§ Ø§Ù„Ù…Ø§Ù„ ØŒ Ùˆ Ù‚Ù„ÙˆØ¨Ù‡Ø§ Ø­Ù‚ÙˆØ¯Ù‡ Ø¨Ø³ ØªØ·Ø§Ù„Ø¹ Ø§Ù„ÙŠ Ø¹Ù†Ø¯ ØºÙŠØ±Ù‡Ø§ Ùˆ Ù…Ø§ØªØ­Ù…Ø¯ Ø±Ø¨Ù‡Ø§ !!!]]></document>
		<document><![CDATA[Ø§Ù„Ù„Ù‡Ù… ÙŠÙ‘ Ù…ØºÙŠØ± Ø§Ù„Ø§Ø­ÙˆØ§Ù„ ØºÙŠØ± Ø­Ø§Ù„ÙŠÙ‘ Ø¥Ù„Ù‰ Ø£Ø­Ø³Ù† Ø§Ù„Ø§Ø­ÙˆØ§Ù„ ÙˆÙŽ Ø³Ø®Ø± Ù„ÙŠÙ‘ Ù…Ù† Ø­Ø¸ÙˆØ¸ Ø§Ù„Ø¯Ù†ÙŠØ§ Ù…Ø§ ØªØ¹Ù„Ù… Ø£Ù†Ù‡Ø§ Ø®ÙŠØ± Ù„ÙŠÙ‘ ÙˆÙŽ Ø£ØµØ±Ù Ø¹Ù†ÙŠ ÙƒÙ„ Ù…Ø§ Ù‡Ùˆ Ø´Ø± Ù„ÙŠÙ‘.]]></document>
		<document><![CDATA[Ø¥ÙÙ„Ù‰ Ø§Ù„Ù„Ù‡ Ø£Ø´ÙƒÙˆ Ù„Ø§ Ø¥ÙÙ„Ù‰ Ø§Ù„Ù†Ø§Ø³ Ø£Ø´ØªÙƒÙŠØŒ
Ø£Ø±Ù‰Ù° Ø§Ù„Ø£Ø±Ø¶ ØªØ¨Ù‚Ù‰ ÙˆØ§Ù„Ø£Ø®Ù„Ù‘Ø§Ø¡ ØªÙŽØ°Ù’Ù‡ÙŽØ¨ÙðŸ’”.]]></document>
		<document><![CDATA[Ø£Ù†Ø§ Ø¹Ù„Ù‰ Ù‚Ù†Ø§Ø¹Ø© Ø¨Ø¥Ù†ÙŠ Ø´Ø®Øµ Ø¹Ø§Ø¯ÙŠ ØŒ 
Ù„ÙƒÙ† Ù…ØªØ£ÙƒØ¯Ø© Ø¥Ù† Ø¹Ø§Ø¯ÙŠØªÙŠ Ù„Ø§ ØªÙÙ†Ø³Ù‰ ÙˆÙ„Ø§ ØªØªØ´Ø§Ø¨Ù‡ Ù…Ø¹ Ø£Ø­Ø¯.]]></document>
		<document><![CDATA[ÙÙŠÙ Ø§Ù„Ù†Ù‡Ø§ÙŠÙÙ‡ Ù†Ø­Ù†Ù Ù…Ø¯ÙÙŠÙ†ÙˆÙ† Ø¨Ø§Ø§Ù„Ø¢Ø¹ØªØ°Ø§Ø±Ù Ù„Ø¢Ù†ÙÙØ³Ù†Ø§ Ù„Ø¢Ù†ÙÙ†Ø§ Ø­Ù„ÙÙ…Ù†Ø§ Ø¨Ø¢Ø­Ù„Ø§Ù…Ù Ù„Ù… ØªÚ¯Ù†Ù ÙŠÙˆÙ…ÙØ§ Ù…Ù†Ù Ø­Ù‚ÙÙ†Ø§.]]></document>
		<document><![CDATA[ÙÙŠ Ù†Ø§Ø³ Ø¹Ù„Ù‰ ÙƒØ«Ø± Ù…Ø§ ÙƒÙ†Ø§ Ù†Ø­Ø¨Ù‡Ù… Ø§Ù„Ø­ÙŠÙ† Ø·Ø§Ø±ÙŠÙ‡Ù… Ø¨Ø³ ÙŠØ³Ø¯ Ø§Ù„Ù†ÙØ³ðŸ‘ŒðŸ¼.]]></document>
		<document><![CDATA[Ø±Ø­Ù€Ù… Ø§Ù„Ù„Ù‡ Ù…Ù€Ù† ÙƒØ§Ù†Ù€ÙˆØ§ Ù„Ù„Ø¹ÙŠÙ€Ø¯ ÙÙ€Ø±Ø­Ù‡ ÙˆØ­ÙŠØ§Ø©ØŒ Ø§Ù„Ù„Ù‡Ù… Ø§ØºÙØ± Ù„Ù‡Ù€Ù… ÙˆØ§Ø³ÙƒÙ†Ù‡Ù€Ù… ÙØ³ÙŠÙ€Ø­ Ø¬Ù†Ø§ØªÙ€ÙƒðŸ’”]]></document>
		<document><![CDATA[#Ø´ÙƒØ±Ø§_Ù„Ùƒ ÙŠØ§ Ø§Ù…ÙŠ Ø¹Ù„Ù‰ ÙˆØ¬ÙˆØ¯Ùƒ Ø¨Ø¬Ø§Ù†Ø¨ÙŠ Ø¯Ø§Ø¦Ù…Ø§Ù‹ ðŸ’ž]]></document>
		<document><![CDATA[Ø±Ø§Ø­Ù€Û ÙŠØ§Ù„Ù„Ù‡ Ø­ØµÙ‘Ù† Ø¨Ù‡Ø§ Ù‚ÙÙ„Ø¨Ù€ÙŠ Ù…Ù† ÙƒÙÙ„ Ø´Ø¹ÙˆØ± ..!]]></document>
		<document><![CDATA[Ù‚Ø±Ø¨ Ø§Ù„Ø¹ÙŠØ¯ 
Ø§Ù†ØªØ¨Ù‡ ØªØ¶Ø­Ùƒ Ø¹Ù„Ù‰ Ù„Ø¨Ø³ Ø£Ø­Ø¯ Ø§Ùˆ ØªÙ‚Ø¯ÙŠÙ… Ø£Ø­Ø¯ ØŒ Ù…Ø§ÙÙŠ Ø§Ù„ØµØ¯ÙˆØ± ÙˆØ§Ù„Ø¨ÙŠÙˆØª Ø¸Ø±ÙˆÙ Ù„Ø§ÙŠØ¹Ù„Ù…Ù‡Ø§ Ø¥Ù„Ø§ Ø§Ù„Ù„Ù‡ ØŒ ÙƒÙˆÙ†ÙˆØ§ Ù„ÙØ·ÙØ§Ø¡ Ø¥Ù† Ù„Ù… ØªØ­Ø³Ù†ÙˆØ§ Ù„Ø§ØªØ¶Ø±ÙˆØ§ ÙˆÙ„Ø§ØªØ¬Ø±Ø­ÙˆØ§]]></document>
		<document><![CDATA[Ø®Ù…Ø³Ø© Ù„Ù† Ø§Ø³Ø§Ù…Ø­Ù‡Ù…  ðŸ–ðŸ»
Ù…Ù† ØŒ ÙØ±Ù‚ Ø¨ÙŠÙ†ÙŠ ÙˆØ¨ÙŠÙ† Ø£Ø¹Ø² Ø§Ù„Ù†Ø§Ø³ 
Ù…Ù† ØŒ ØªÙƒÙ„Ù… Ø¨Ø®Ù„ÙÙŠ ÙˆØ§Ø¨ØªØ³Ù… Ø¨ÙˆØ¬Ù‡ÙŠ
Ù…Ù† ØŒ Ø¸Ù„Ù…Ù†ÙŠ ÙˆÙ‚Ù‡Ø± Ù‚Ù„Ø¨ÙŠ
Ù…Ù† ØŒ Ø£Ø­Ø¨Ù†ÙŠ ÙƒØ°Ø¨Ø§
Ù…Ù† ØŒ ÙŠØ´ÙˆÙ‡ Ø³Ù…Ø¹ØªÙŠ Ø¨ÙƒØ°Ø¨Ù‡]]></document>
		<document><![CDATA[Ø³Ù…ÙŠØª " Ù„ÙŠÙ„Ø© Ø§Ù„Ù‚Ø¯Ø±"  Ù„Ø§Ù† Ø§Ù‚Ø¯Ø§Ø±Ù†Ø§ ÙŠÙ…ÙƒÙ† Ø§Ù† ØªØªØºÙŠØ± ÙÙŠÙ‡Ø§Ø›ÙŠØ§Ø±Ø¨ Ø¨Ù„ØºÙ†Ø§ Ø£ÙŠØ§Ù‡Ø§
Ø§Ù„Ù„Ù‡Ù… Ø§Ø¬Ø¹Ù„Ù†ÙŠ Ù…Ù† Ø§Ù„Ø°ÙŠÙ† ØºÙŠØ±Øª Ø§Ù‚Ø¯Ø§Ø±Ù‡Ù… Ù„Ù„Ø§ÙØ¶Ù„ ÙˆØ§Ø±Ø²Ù‚Ù†ÙŠ Ù†Ø¹ÙŠÙ… Ø§Ù„Ø¯Ù†ÙŠØ§ ÙˆØ§Ù„Ø§Ø®Ø±Ø©ðŸ’—.]]></document>
		<document><![CDATA[ÙÙŠÙ‡ Ù†Ø§Ø³ Ù…Ø±ÙƒØ²ÙŠÙ† Ø¨Ø­ÙŠØ§ØªÙŠ Ø§ÙƒØ«Ø± Ù…Ù†ÙŠ .]]></document>
		<document><![CDATA[Ø§ÙŠ ÙˆØ§Ù„Ù„Ù‡ðŸ˜‚ðŸ˜‚ https://t.co/gK4MPksm3b]]></document>
		<document><![CDATA[@deviloo2 ÙŠØ§Ø®Ø° Ù…Ù†Ùˆ ðŸ‘€]]></document>
		<document><![CDATA[Ø£Ù‚Ø¯Ø± Ø£ÙƒÙÙˆÙ† Ø§Ù„Ù„Ø¹Ù†Ø© ÙˆÙ†Ø¯Ù‘Ù… Ø¹ÙÙ…Ø±Ùƒ Ø¥Ù†Ùƒ Ø¹Ø±ÙØªÙ†ÙŠ,ÙˆØ£Ù‚Ø¯Ø± Ø§ÙƒÙÙˆÙ† Ø§Ù„Ø¬Ø§Ù†Ø¨ Ø§Ù„Ø­Ù„ÙÙˆ Ø¨Ø­ÙŠØ§ØªÙƒ ÙˆÙƒÙ„Ù‡ ØªØ­Ø¯Ø¯Ù‘Ù‡ Ø£Ù†Øª.]]></document>
		<document><![CDATA[ÙˆØ³ÙŠÙÙ‚Ø¶ÙŠ Ø§Ù„Ù„Ù‡ Ø£Ù…Ø±Ø§Ù‹ ÙƒÙ†Ù‘Øª ØªØ­Ø³Ø¨Ù‡Ù Ø¨Ø³ÙˆØ¡Ù Ø¸Ù†Ùƒ Ù…ÙØ³ØªØ­ÙÙŠÙ„Ø§Ù‹.]]></document>
		<document><![CDATA[@sarounaxx @deviloo2 Ø§Ø³ØªÙ‚Ø¨Ù„ ØªØ±Ù‰ ðŸ™„ðŸ’‹â¤ï¸ https://t.co/kMnu86rT3D]]></document>
		<document><![CDATA[Ø§Ù„Ù„Ù‡Ù… Ø¥Ù†ÙŠ Ø£Ø³ØªÙˆØ¯Ø¹ØªÙƒ Ù†ÙØ³ÙŠ ÙˆØ¹Ø§Ø¦Ù„ØªÙŠ Ù…Ù† ÙƒÙ„ Ø´Ø±]]></document>
		<document><![CDATA[Ø±Ø¨ÙŠ Ø£Ù†Øª Ø§Ù„ÙˆØ­ÙŠØ¯ Ø§Ù„Ø°ÙŠ ØªÙØ¹Ø·ÙŠ ÙˆÙ„Ø§ ØªÙ…Ù† Ø¨Ø¹Ø·Ø§Ø¦Ùƒ Ø§Ù„ÙƒØ±ÙŠÙ… Ø±Ø¨ÙŠ Ø±Ø¬ÙˆØªÙƒ ÙØ±Ø­Ø© Ù…Ù† Ø¹Ù†Ø¯Ùƒ ØªØ³Ø±Ù Ø¨Ù‡Ø§ Ø®Ø§Ø·Ø±ÙŠ!]]></document>
		<document><![CDATA[Ø£Ø¹ÙÙˆØ° Ø¨Ø§Ù„Ù„Ù‡ Ù…Ù† Ø­Ø²Ù†ÙŒ ÙŠØ·ÙˆÙŠÙ†Ø§ ÙˆØ°Ù†Ø¨ÙŒ ÙŠØ­Ø¨Ø³ ÙØ±Ø­ØªÙ†Ø§ Ø£Ø¹ÙÙˆØ° Ø¨Ø§Ù„Ù„Ù‡ Ù…Ù† Ù‡Ù…ÙÙˆÙ… Ø§Ù„Ø¯Ù†ÙŠØ§ ÙˆÙ…Ø§ ÙÙŠÙ‡Ø§ ðŸ’›.]]></document>
		<document><![CDATA[Ù§ Ø±Ù…Ø¶Ø§Ù† | ÙŠØ³ÙÙ‘Ø± Ø§Ù„Ù„Ù‡ÙÙ… Ø£Ù…Ø±ÙŠ Ø¥Ù†Ù†ÙŠ Ø§Ù„Ø¹Ø¨Ø¯ Ø§Ù„Ø¶Ø¹ÙŠÙØŒ ÙˆØ¥Ø´Ø±Ø­ Ø§Ù„Ù„Ù‡ÙÙ… ØµØ¯Ø±ÙŠ Ø¥Ù†Ùƒ Ø§Ù„Ø¨Ø§Ø±ÙŠ Ø§Ù„Ø±Ø¦ÙŠÙ ðŸ’›.]]></document>
		<document><![CDATA["ÙƒÙ† ÙˆØ§Ø«Ù‚Ø§Ù‹ Ù…Ø·Ù…Ø¦Ù†Ø§Ù‹ Ø¨Ø£Ù† Ù„Ø§ Ø£Ø­Ø¯ ÙŠÙ‚Ø¯Ø± Ø£Ù† ÙŠØºÙ„Ù‚ Ø¨Ø§Ø¨Ø§Ù‹ Ù‚Ø¯ ÙØªØ­Ù‡ Ø§Ù„Ù„Ù‡ Ù„Ùƒ".]]></document>
		<document><![CDATA[Ø§Ù†Ø§ Ù…Ø³ØªØ­ÙŠÙ„ Ø§ØªØ£Ø®Ø± Ø¨Ø§Ù„Ø±Ø¯ Ø§Ù„Ø§ Ø¨Ø«Ù„Ø§Ø« Ø­Ø§Ù„Ø§Øª ÙŠØ§ Ø§Ù„Ù†Øª ØªØ¨Ù† Ø§Ùˆ Ø§ØªØ§Ø¨Ø¹ Ù…Ø³Ù„Ø³Ù„ Ø§Ùˆ Ù†Ø§ÙŠÙ…Ø© Ø­Ø±ÙƒØ§Øª Ø§Ù„Ø«Ù‚Ù„ Ù‡Ø§ÙŠ Ù…Ø§Ø¹Ø±ÙÙ‡Ø§Ø­]]></document>
		<document><![CDATA[Ø¨Ø¹Ø¶ Ø§Ù„Ø¨Ø´Ø± ÙŠÙ†Ø·Ø¨Ù‚ Ø¹Ù„ÙŠÙ‡Ù… Ù‡Ø°Ø§ Ø§Ù„Ù…Ø«Ù„ :  
Ø£Ø­Ø³Ù†Øª Ù„Ù€Ù‡ Ø¯Ù‡Ø±Ø§Ù‹ ÙˆØ£Ø³Ø£Øª Ù„Ù€Ù‡ ÙÙŠ ÙŠÙˆÙ…
ÙÙ€ Ù†Ø³Ù‰ Ø§Ù„Ø¯Ù‡Ø±!  Ùˆ ØªØ°ÙƒØ± Ø§Ù„ÙŠÙˆÙ…!]]></document>
		<document><![CDATA[Ù¥ | Ø±Ù…Ø¶Ø§Ù†Â 
Ø£ÙˆÙ„ Ø¬Ù…Ø¹Ù‡ ÙÙŠ Ø´Ù‡Ø± Ø±Ù…Ø¶Ø§Ù† Ø§Ù„Ù…Ø¨Ø§Ø±Ùƒ 
Ø§Ù„Ù„Ù‡Ù… Ø¥Ø±Ø²Ù‚Ù†Ø§ Ø¥Ø³ØªØ¬Ø§Ø¨Ù‡ Ù„Ø¯Ø¹Ø§Ø¦Ù†Ø§ Ùˆ Ø£Ù…Ø§Ù†ÙŠÙ†Ø§ Ø§Ù„Ù…Ù†ØªØ¸Ø±Ù‡..]]></document>
		<document><![CDATA[@deviloo2 @sarounaxx Ù…Ø§Ø¹Ù„ÙŠÙ‡ Ø§Ø°Ø§ Ù…Ø¯Ù‰ Ø§Ø³ÙˆÙŠ Ù„Ø¬ Ø¹ÙŠÙˆÙ†ÙŠ Ù„Ø¬ðŸŒš]]></document>
		<document><![CDATA[@sarounaxx @deviloo2 ØªÙ‚Ø·Ø¹ ÙˆØ§Ù„Ù„Ù‡ÙŠ ðŸ’” Ø§Ù†Ø·Ø± Ø¨Ø§Ø¬Ø± Ø¹Ù„Ù‰ Ø§Ø­Ø± Ù…Ù† Ø§Ù„Ø¬Ù…Ø± ðŸ”¥]]></document>
		<document><![CDATA[@deviloo2 @sarounaxx Ø´ØªØª ØªØ°ÙƒØ±Øª ÙˆØ­Ø¯Ù‡ Ù„Ø¹Ù†ØªÙŠ Ø®ÙŠØ±Ù‡Ø§ Ø§Ø®Ø®Ø®ðŸ˜‚ðŸ˜‚ðŸ˜‚ðŸ’”]]></document>
		<document><![CDATA[Ù„Ø§ Ù†Ù„ÙŠÙ‚ Ø¨Ø§Ù„Ø­Ø¨ ÙŠØ§Ø³ÙŠØ¯ÙŠ
ÙØ£Ù†ØªÙ‡ ØªÙƒØ§Ø¨Ø± ÙˆØ£Ù†Ø§ Ù„Ø§ Ø£Ù†Ø­Ù†ÙŠ.

#Ù†Ø²Ø§Ø±_Ù‚Ø¨Ø§Ù†ÙŠ]]></document>
		<document><![CDATA[@sarounaxx Ù„Ø§ ØªÙƒÙÙŠÙ† Ø³Ø§Ù…Ø­ÙŠ ðŸ˜­]]></document>
		<document><![CDATA[Ø§Ù„Ù„Ù‡ÙÙ‘Ù… Ø£ÙƒØªØ¨ Ù„ÙŠ Ø­Ø³Ù† Ø§Ù„Ø®Ø§ØªÙ…Ø© ÙˆÙ†Ø¹ÙŠÙ… Ø§Ù„Ø¬Ù†Ø© ..]]></document>
		<document><![CDATA[ÙÙŠÙ‡ Ø´Ø¹ÙˆØ± ÙŠØ¬Ø¨Ø±Ùƒ Ø¹Ù„Ù‰ Ø§Ù„ØµÙ…Øª ØŒØ§Ù„ØµÙ…Øª Ø§Ù„Ù„ÙŠ ÙŠÙ†Ø³Ù‘ÙŠÙƒ Ø¨Ø¹Ø¯Ù‡ ÙƒÙŠÙ ØªØ¨Ø¯Ø£ Ø§Ù„ÙƒÙ„Ø§Ù…..]]></document>
		<document><![CDATA[ÙŠØ§ Ø¬Ø§Ù…Ø¹ Ø§Ù„Ù†Ø§Ø³ ÙÙŠ ÙŠÙˆÙ… Ù„Ø§ Ø±ÙŠØ¨ ÙÙŠÙ‡ØŒ Ø§Ø¬Ù…Ø¹ Ø¨ÙŠÙ†ÙŠ ÙˆØ¨ÙŠÙ† Ø³Ø¹Ø§Ø¯ØªÙŠØŒ ØªÙˆÙÙŠÙ‚ÙŠØŒ Ø¥Ø±ØªÙŠØ§Ø­ÙŠØŒ Ø§Ø·Ù…Ø¦Ù†Ø§Ù†ÙŠØŒ Ù‡ÙØ¯Ø§ÙŠØŒ ÙˆÙƒÙ„ Ø£Ù…Ø± ÙŠØ³Ø±Ù†ÙŠ ÙŠØ§Ù„Ù„Ù‡â¤ï¸]]></document>
		<document><![CDATA[@deviloo2 @sarounaxx Ù…Ø§ Ø§Ù†Ø­Ø±Ù…Ù…Ù… ðŸ’–ðŸ’–]]></document>
		<document><![CDATA[Ù„Ø§ ØªÙ‡ØªÙ… Ø£Ø¨Ø¯Ø§Ù‹ Ù„Ù…Ø§ ÙŠÙÙ‚Ø§Ù„ Ù„Ùƒ ØŒ Ø¥Ù‡ØªÙ… Ù„Ù…Ø§ ÙŠÙÙØ¹ÙŽÙ„ Ù…Ù† Ø£Ø¬Ù„Ùƒ .]]></document>
		<document><![CDATA[ØªØªØ¹Ø§Ù…Ù„ Ø¨Ù„Ø·Ù = Ù‚Ø§Ø· Ø¹Ù…Ø±Ùƒ ðŸ’¦
ØªØªØºØ´Ù…Ø± ÙˆØªØ¶Ø­Ùƒ = Ø®ÙÙŠÙ ðŸ’”
ØªØªØ¹Ø§Ù…Ù„ Ø¨Ø«Ù‚Ù„ = Ù…ØºØ±ÙˆØ± ðŸš¶
ØªÙ„Ø¹Ù† ÙˆØ§Ù„Ø¯ÙŠÙ†Ù‡Ù… = ÙŠÙ…Ø´ÙˆÙ† Ø³ÙŠØ¯Ù‡ ðŸ‘ŒðŸ½]]></document>
		<document><![CDATA[Ø³ÙŠØ¯Ù†Ø§ ÙŠÙˆØ³Ù Ø¯Ø®Ù„ Ø§Ù„Ø³Ø¬Ù† Ø¨Ø³Ø¨Ø¨ Ø§Ù…Ø±Ø£Ù‡
Ø³Ù„ÙŠÙ…Ø§Ù† Ø­Ø±Ùƒ Ø§Ù„Ø¬Ù† Ù„Ø¬Ù„ Ø§Ù…Ø±Ø£Ù‡
Ù‡ØªÙ„Ø± Ø­Ø±Ù‚ Ø§Ù„ÙŠÙ‡ÙˆØ¯ Ø¨Ø³Ø¨Ø¨ Ø§Ù…Ø±Ø£Ù‡ 
Ø±ÙˆÙ…ÙŠÙˆ Ø§Ù†ØªØ­Ø± Ø¨Ø³Ø¨Ø¨ Ø§Ù…Ø±Ø£Ù‡
ÙˆÙŠØ¬ÙŠÙƒ Ø­ÙŠÙˆØ§Ù† ÙŠÙ‚ÙˆÙ„Ùƒ Ø§Ù„Ø¨Ù†Ø§Øª Ù„Ø¹Ø¨ØªÙŠ]]></document>
		<document><![CDATA[Ø£Ø¹Ù…Ù“Ù‰ Ø§Ù„Ø¹ÙŠÙ† Ù‚Ù“Ø¯ ÙŠÙØ¨ØµØ± ÙŠÙˆÙ…Ù‹Ø§ .. Ø¨ÙŠÙ†Ù…Ø§ Ø£Ø¹Ù…Ù“Ù‰ Ø§Ù„Ù‚Ù„Ø¨ .. Ù„Ù† ÙŠÙØ¨ØµØ± Ø£Ø¨Ø¯Ø§Ù‹ !]]></document>
		<document><![CDATA[@deviloo2 Ø§Ø®Ø±ØµÙŠ Ø®Ù„Ø§Ø§Ø§Ø§Ø§Ø§Øµ Ù„Ø§ Ø§Ù†Ø§Ø¯ÙŠ Ø®Ø·ÙŠØ¨Ø¬ðŸ˜‚ðŸ˜˜]]></document>
		<document><![CDATA[@deviloo2 Ø¹Ù„Ù‰ Ø§Ù„Ø§Ø³Ø§Ø³ Ø§Ù†ØªÙŠ Ù…Ùˆ Ø¨Ø§Ù‚ÙŠØªÙ‡ðŸ˜’ðŸ‘ðŸ»]]></document>
		<document><![CDATA[Ø£Ø¨Ø³Ø£Ù„ÙƒØŸ
ÙŠØ§ Ø§Ø¬Ù…Ù„ Ø§Ù†ÙˆØ§Ø¹ Ø§Ù„ØµØ¨Ø±
Ù„ÙŠÙ‡ Ø§Ù†ØªØ¸Ø± ØŸ
ÙˆØ§Ù†Ø§ Ø§Ø¯Ø±ÙŠ Ø§Ù† ÙÙ€ Ø­Ø§Ù„ØªÙŠ Ù…Ø§ ÙÙŠ Ø§Ù…Ù„
Ù„Ùˆ Ø§Ù†ØªØ¸Ø± ÙƒÙ„ Ø§Ù„Ø¹Ù…Ø±ØŸ]]></document>
		<document><![CDATA[Ù‚Ø¨Ù„ Ù„Ø§ØªØªÙƒÙ„Ù… Ø¹Ù† Ø§Ø­Ø¯ Ø®Ø° Ù„ÙÙ‡ Ø¹Ù„Ù‰ Ù†ÙØ³Ùƒ ÙŠØ§ÙƒØ§Ù…Ù„ Ø§Ù„Ø£ÙˆØµØ§Ù.]]></document>
		<document><![CDATA[Ø§Ù„Ù„Ù‡ÙÙ…Ù‘ Ø¥Ø±Ø­Ù… Ø¶ÙØ¹ÙÙŽ Ø¨Ø¯Ù†ÙŠØŒ ÙˆØ±Ù‚Ø© Ø¬Ù„Ø¯ÙŠ ÙˆØ¯Ù‚Ø© Ø¹Ø¸Ù…ÙŠðŸ™ðŸ».]]></document>
		<document><![CDATA[Ø±Ø¨ÙŠ Ø£Ø³Ø¹Ø¯ Ø£Ù…ÙŠ Ø¹Ø¯Ø¯ Ù…Ø§ Ø¶Ø® Ù‚Ù„Ø¨Ù‡Ø§ ÙˆØ¹Ø¯Ø¯ Ù…Ø§Ø±Ù…Ø´Øª Ø¹ÙŠÙ†ÙŠÙ‡Ø§ ÙˆØ£Ø¨Ø¹Ø¯ Ø¹Ù†Ù‡Ø§ ÙƒÙÙ„ Ø³ÙˆØ¡ ÙŠØ§Ù„Ù„Ù‡.]]></document>
		<document><![CDATA[Ù„ÙŠØ³ Ù‡Ù†Ø§Ùƒ Ø±Ø¬Ù„ ÙŠØ³ØªØ­Ù‚ Ø£Ù† ØªØ¨ÙƒÙŠ Ù…Ù† Ø£Ø¬Ù„Ù‡ ØŒ ÙˆÙ„Ø§ØªØµØ¯Ù‚ÙŠ Ø£Ù†Ù‡ Ø­Ø²ÙŠÙ† Ù„ÙØ±Ø§Ù‚Ùƒ ØŒØŒ ÙÙ€Ù€ Ø¯Ø§Ø¦Ù…Ø§Ù‹ Ø¹Ù†Ø¯ ÙƒÙ„ Ø´Ø±Ù‚ÙŠ Ø¨Ø¯Ø§Ø¦Ù„ !

#Ù†Ø²Ø§Ø±_Ù‚Ø¨Ø§Ù†ÙŠ]]></document>
		<document><![CDATA[Ø³Ù„Ø§Ù… Ø¹Ù„Ù‰ Ø§Ù„Ù…Ø¨ØªØ³Ù…ÙŠÙ†ØŒ Ùˆ ÙÙŠ Ø£ÙØ¦Ø¯ØªÙ‡Ù… Ø®Ù†Ø§Ø¯Ù‚ Ø§Ø­Ø²Ø§Ù† Ø£ÙˆÙ„Ø¦Ùƒ Ø§Ù„Ø°ÙŠÙ† Ù‚Ø±Ø±ÙˆØ§ Ø§Ù„Ø­ÙŠØ§Ø© ÙˆÙ„Ùˆ Ù„Ù… ØªØ­Ø§Ù„ÙÙ‡Ù… Ø§Ù„Ù†Ø¨Ø¶Ø§Øª..]]></document>
		<document><![CDATA["ÙŠØ¨Ù‚Ù‰ Ø§Ù„Ø´ÙˆÙ‚ Ù„Ø±Ù…Ø¶Ø§Ù† ÙŠØªÙƒØ±Ø± ÙƒÙ„ Ø³Ù†Ù‡ ÙˆÙƒØ£Ù†Ù‡ Ù…ÙÙ‚Ø¨Ù„ Ø¹Ù„ÙŠÙ†Ø§ Ø£ÙˆÙ„ Ù…Ø±Ù‡ ÙŠØ§Ø±Ø¨Ù‘ Ø¨Ù„ØºÙ†Ø§ Ø±Ù…Ø¶Ø§Ù† Ù„Ø§ ÙØ§Ù‚Ø¯ÙŠÙ† ÙˆÙ„Ø§ Ù…ÙÙ‚ÙˆØ¯ÙŠÙ†".]]></document>
		<document><![CDATA[Ø³Ø¨Ø­Ø§Ù† Ø§Ù„Ø°ÙŠ Ø£Ø³Ø±Ù‰ Ø¨Ø¹Ø¨Ø¯Ù‡ Ù„ÙŠÙ„Ø§ Ù…Ù† Ø§Ù„Ù…Ø³Ø¬Ø¯ Ø§Ù„Ø­Ø±Ø§Ù… Ø¥Ù„Ù‰ Ø§Ù„Ù…Ø³Ø¬Ø¯ Ø§Ù„Ø£Ù‚ØµÙ‰ Ø§Ù„Ø°ÙŠ Ø¨Ø§Ø±ÙƒÙ†Ø§ Ø­ÙˆÙ„Ù‡ Ù„Ù†Ø±ÙŠÙ‡ Ù…Ù† Ø¢ÙŠØ§ØªÙ†Ø§ ÛšØ¥Ù†Ù‡ Ù‡Ùˆ Ø§Ù„Ø³Ù…ÙŠØ¹ Ø§Ù„Ø¨ØµÙŠØ±]]></document>
		<document><![CDATA[Ø§Ù†Ø§ Ø§ÙƒØ«Ø± Ø§Ù†Ø³Ø§Ù†Ø© ØªÙ…Ø´ÙŠ Ø§Ù„Ù…ÙˆØ¶ÙˆØ¹ ÙˆØªØ³ÙˆÙŠ Ø±ÙˆØ­Ù‡Ø§ Ù…Ø§ØªØ¯Ø±ÙŠ Ø¹Ù† Ø´ÙŠØŒ Ù„ÙƒÙ† Ø§Ù„Ø­Ù‚ÙŠÙ‚Ø© ÙƒØ§Ø´ÙÙ‡ Ø§Ù… Ø§Ù„ÙˆØ¶Ø¹ØŒØ¨Ø³ Ø§Ø³ØªØºØ¨Ù‰ Ø¨Ù…Ø²Ø§Ø¬ÙŠ .]]></document>
		<document><![CDATA[Ø§Ù†Ø§ Ø§Ù…Ø±Ø£Ø© Ø¹Ù†ÙˆØ§Ù†ÙŠ Ø£Ù„Ø§Ù‘ Ø£Ø±ÙƒØ¹ Ù„Ø£ÙŠÙ‘ Ø¥Ù†Ø³Ø§Ù†]]></document>
		<document><![CDATA[ØµØ¯ÙŠÙ‚ ÙŠØ¹Ø²Ùƒ ÙˆÙ„Ø§ Ø­Ø¨ÙŠØ¨ ÙŠØ°Ù„ÙƒðŸ‘ðŸ¼]]></document>
		<document><![CDATA[Ù…Ù† Ù‚Ø§Ù„ Ø£Ù†Ù‘ÙŠ "ÙƒØªÙˆÙ…"
Ø¨Ø­Øª Ù„ Ø±Ø¨Ù‘ÙŠ ÙƒÙ„ Ø´ÙŠØ¡â¤ï¸]]></document>
		<document><![CDATA[Ø§Ù‚ØªØ±Ø¨ÙŽ Ø§Ù„Ù…ÙˆØªÙ Ù…Ù†ÙÙ‘ÙŠ Ù‚Ù„ÙŠÙ„Ø§Ù‹ ÙÙ‚Ù„ØªÙ Ù„Ù‡: ÙƒØ§Ù† Ù„ÙŠÙ„ÙŠ Ø·ÙˆÙŠÙ„Ø§Ù‹ ÙÙ„Ø§ ØªØ­Ø¬Ø¨ Ø§Ù„Ø´Ù…Ø³ÙŽ Ø¹Ù†Ù‘ÙŠ]]></document>
		<document><![CDATA[Ù„Ø§ Ø§Ù„Ø´ÙØ¹Ù’Ø±Ù Ø´ÙØ¹Ù’Ø±ÙŒ ÙˆÙ„Ø§ Ø§Ù„Ù†ÙŽØ«Ù’Ø±Ù Ù†ÙŽØ«Ù’Ø±ÙŒ ÙˆØ£ÙŽÙ†ØªÙ ØªÙ‚ÙˆÙ„ÙŠÙ†: Ù„Ù† Ø£ÙŽØ¯ÙŽØ¹ÙŽÙƒÙ’ØŒ ÙØ®ÙØ°Ù’Ù†ÙŠ Ø¥Ù„ÙŠÙƒØŒ ÙˆØ®ÙØ°Ù’Ù†ÙŠ Ù…ÙŽØ¹ÙŽÙƒÙ’!]]></document>
		<document><![CDATA[Ù„Ø§ ØªØ¨ØªØ¹Ø¯ Ø§Ø±Ø¬ÙˆÙƒ ØŒ ØªØ¹Ø¨ØªÙ†ÙŠ ÙˆÙŠØ§Ùƒ ..]]></document>
		<document><![CDATA[Ø§Ù†Ø§ ÙˆØ§Ù„Ù„Ù‡ Ø§Ø¨Ø¯ Ù…Ø§ Ø®Ù†Ù‘Øª ÙˆÙ„Ø§ ÙÙƒØ±Øª Ø¨Ø§Ù„Ù†Ø³ÙŠØ§Ù†! 
Ùˆ Ø§Ø°Ø§ ØªÙ‚ÙˆÙ‰ Ø§Ù†Ø§ Ù…Ø§Ù‚ÙˆÙ‰..]]></document>
		<document><![CDATA[ÙŠÙŽ Ø¬ÙˆØ§Ø¨ÙŠ ÙŠÙˆÙ… Ù‚Ø§Ù„Ùˆ ÙˆØ´ ÙŠØ³Ø¹Ø¯ÙƒðŸ’™.]]></document>
		<document><![CDATA[ØªØ£Ø«ÙŠØ± Ø¹ÙŠÙˆÙ†ÙÙƒ Ø¹Ù„Ù‰ Ù‚Ù„Ø¨ÙŠ,Ø§Ù‚ÙˆÙ‰ Ù…ÙÙ† Ø£Ù„Ù Ø£ÙØºÙ†ÙŠÙ‡.]]></document>
		<document><![CDATA[Ù„Ø§ ÙŠØ®ÙÙŠÙ†ÙŠ Ø¶Ø¹ÙÙŠ Ø¨Ù‚Ø¯Ø± Ù…Ø§ØªØ®ÙŠÙÙ†ÙŠ Ù‚ÙˆØªÙŠØŒØ§Ø®Ø§Ù Ø§Ù„Ø§ Ø§Ù†Ø­Ù†ÙŠ ÙŠÙˆÙ…Ø§Ù‹ Ø­ÙŠÙ† ÙŠÙ„Ø²Ù…Ù†ÙŠ Ø§Ù„Ø§Ù†Ø­Ù†Ø§Ø¡.]]></document>
		<document><![CDATA[Ø­ØªÙ‰ Ù…Ø®ÙŠ ØµØ§ÙŠØ± ÙŠØ±ÙØ¹ Ø¶ØºØ·ÙŠØŒ Ø¹Ù„Ù‰ ÙƒÙŠÙÙ‡ ÙŠÙÙƒØ± Ø¨Ø£Ø´ÙŠØ§Ø¡ Ù…Ø§Ø¨ÙŠ Ø§ÙÙƒØ± ÙÙŠÙ‡Ø§.]]></document>
		<document><![CDATA[ÙƒÙ† ØµØ¨ÙˆØ±Ø§Ù‹ ÙÙŠ ÙƒÙ„ Ø´ÙŠØ¡ ØŒ Ù‚Ù„:Ø§Ù„Ø­Ù…Ø¯Ø§Ù„Ù„Ù‡ Ø¯ÙˆÙ…Ø§Ù‹ ÙÙƒÙ… Ù…Ù† ØµØ¯Ø±Ù Ø¶Ø§Ù‚ ØŒ Ø«Ù… Ø¨Ø±Ø­Ù…Ø© Ø§Ù„Ù„Ù‡ Ø§ØªØ³Ù€Ø¹ðŸ’—.]]></document>
		<document><![CDATA[Ù„Ø§ ØªÙŠØ£Ø³Ù‘ ÙÙŽ ÙˆØ§Ù„Ù„Ù‡ Ù…ÙŽØ§ Ø°Ø¨ÙŽÙ„ØªÙ‘ Ø¹ÙÙŠÙ† Ø¥Ù„Ø§ ÙˆÙÙÙˆÙ‚Ù‡Ø§ Ø±ÙŽØ¨Ù‘ ÙŠÙŽØ®Ø¨Ø¦ Ù„Ù‡Ø§ Ø§Ù„Ø£Ø¬Ù…ÙŽÙ„ ..ðŸ’œðŸ™]]></document>
		<document><![CDATA[Ø§Ù†Ø§ ÙŠØ§ ØµØ§Ø­Ø¨ÙŠ Ù…Ù† Ø±Ø§ÙÙ‚ØªÙƒ Ø±Ø§ÙÙ‚ØªÙ†ÙŠ Ø§Ù„Ø³Ø¹Ø§Ø¯Ù‡ ÙŠØ§ Ø¬Ø¹Ù„ Ø±ÙÙ‚ØªÙƒ"Ø¯Ù†ÙŠØ§ ÙˆØ¬Ù†Ù‡"ðŸ’›! @WJ004]]></document>
		<document><![CDATA[ÙÙŠ Ù†Ø§Ø³ Ù…Ø¹ Ø§Ù„Ø§ÙŠØ§Ù… Ù‚Ø§Ø¹Ø¯Ø© Ø§Ù‚ØªÙ†Ø¹ Ø§ÙƒØ«Ø± Ø§Ù†Ù‡ ØµØ¬ ÙØ±Ù‚Ø§Ù‡Ù… Ø¹ÙŠØ¯ .]]></document>
		<document><![CDATA[ã…¤
ã…¤

Ù‡ÙÙ€Ù… Ø¹Ù„Ù€Ù‰ Ø¸Ù†Ù€ÙˆÙ†Ù‡Ù€Ù… ÙŠØ¤Ø«Ù…ÙÙ€ÙˆÙ†
ÙˆØ£Ù†Ù€ØªÙŽ Ø¹Ù„Ù‰ Ø·Ù‡Ù€Ø§Ø±Ø© Ù‚ÙÙ„Ø¨Ù€Ùƒ ØªÙÙ€Ø±Ø²Ù‚ 

- ÙÙ€Ù„Ø§ ØªÙØ¨Ø§Ù„Ù€ÙŠðŸ’œ]]></document>
		<document><![CDATA[Ù‡Ø§ÙŠ Ø£ÙÙ… Ø§Ù„Ø¨Ù†ÙŠÙ† Ø´Ø¹Ù†Ø¯ÙƒÙŽ Ø§Ù†Ø®Ø§Ù‡ÙŽØ§ Ø¨ÙƒÙ„Ù‘ Ø´Ø¯Ø© Ùˆ Ø­Ù‚ Ø¹Ø¨Ø§Ø³ ØªÙ„Ù‚Ø§Ù‡ÙŽØ§.]]></document>
		<document><![CDATA[Ø±Ø¨ÙŠ Ø§Ø­ÙØ¸ Ù„ÙŠ Ø£Ø­Ø¨Ø§Ø¦ÙŠ Ù…Ù† ÙƒÙ„ Ø´Ø± ÙŠØ§Ù„Ù„Ù‡ Ùˆ Ø§Ø­Ù…Ù‡Ù… Ø¨Ø¹ÙŠÙ†Ùƒ Ø§Ù„ØªÙŠ Ù„Ø§ ØªÙ†Ø§Ù… ðŸ’•]]></document>
		<document><![CDATA[Ø£Ø¹ÙˆØ° Ø¨Ø§Ù„Ù„Ù‡ Ø£Ù„Ù Ù…Ø±Ø© Ù…Ù† ÙŠÙˆÙ… Ù„Ø§ Ø£Ø¬Ø¯ ÙÙŠÙ‡ Ø£Ù…ÙŠ ðŸ’—..]]></document>
	</documents>
</author>